Workbook
Name mps_database: mps_database1!$A$1:$E$284

Sheet Neutral_Tandem
A1: Before Renaming | B1: After Renaming | C1: Code 1 | D1: Code 2 | E1: Code 3 | F1: not_OSA_TTS_files
A2: Accounting Detailed Report | B2: Accounting Detailed Report | C2: 0 | D2: 0 | E2: 0 | F2: Adjustments Not Posted Report
A3: Accounting Report | B3: Accounting Report | C3: 0 | D3: 0 | E3: 0 | F3: AUR History Stats
A4: Adjustment & OCC Report | B4: Adjustment & OCC Report | C4: 12Q_ | D4: 0 | E4: 0 | F4: AUR History Stats Report
A5: Adjustment GL Trans by BAN Report | B5: Adjustment Report | C5: 12O_ | D5: 0 | E5: 0 | F5: Bill Completion Check Report
A6: Adjustment GL Trans by BAN Report - New | B6: Adjustment Report | C6: 12O_ | D6: 0 | E6: 0 | F6: Detailed BAN Error Report
A7: Adjustments GL Trans by BAN Report | B7: Adjustment Report | C7: 12O_ | D7: 0 | E7: 0 | F7: Detailed BAN Error Report - with extra research
A8: Adjustments Not Posted Report | B8: Adjustments Not Posted Report | C8: 9F_ | D8: 0 | E8: 0 | F8: Detailed CLLI Error Report
A9: Aged Trial Balance for Export | B9: Aged Trial Balance for Export Report | C9: 0 | D9: 0 | E9: 0 | F9: Detailed CLLI Error Report - with extra research
A10: Aged Trial Balance for Export - New | B10: Aged Trial Balance for Export Report | C10: 0 | D10: 0 | E10: 0 | F10: Duplicate File Processing Report
A11: Aged Trial Balance_for export | B11: Aged Trial Balance for Export Report | C11: 0 | D11: 0 | E11: 0 | F11: Exception Analysis Report
A12: Aged trial Balance | B12: Aged trial Balance Report | C12: 0 | D12: 0 | E12: 0 | F12: Factor Change Audit Report
A13: Aged Trial Balance - New | B13: Aged trial Balance Report | C13: 0 | D13: 0 | E13: 0 | F13: Factor Check Report with PVU
A14: AUR History Stats | B14: AUR History Stats Report | C14: 4A_ | D14: 0 | E14: 0 | F14: Factor Compare Report
A15: AUR History Stats Report | B15: AUR History Stats Report | C15: 4A_ | D15: 0 | E15: 0 | F15: Factor Matrix Report
A16: BAN List with Active Status and LPC Option | B16: BAN List with Active Status and LPC Option | C16: 0 | D16: 0 | E16: 0 | F16: SOC Change Audit Report
A17: Bill By Period Report | B17: Bill By Period Report | C17: 0 | D17: 0 | E17: 0 | F17: Usage Balancing - Company Totals with Full Detail
A18: Bill Completion Check Report | B18: Bill Completion Check Report | C18: 12A_ | D18: 0 | E18: 0 | F18: Usage Balancing - Company, Ban Totals
A19: Billed by Period | B19: Bill By Period Report | C19: 0 | D19: 0 | E19: 0 | F19: Usage Verify by Size Report
A20: Billed by Period Report | B20: Bill By Period Report | C20: 0 | D20: 0 | E20: 0 | F20: MOU Entries Error Report
A21: Billed by Period Report - New | B21: Bill By Period Report | C21: 0 | D21: 0 | E21: 0
A22: Billed Msg MOU Rev by BAN by EMR Jurisdiction | B22: Message MOU Revenue by BAN Report | C22: 0 | D22: 0 | E22: 0
A23: Billed Msg MOU Rev by CLLI by EMR Jurisdiction | B23: Message MOU Revenue by CLLI Report | C23: 0 | D23: 0 | E23: 0
A24: CLNT ly_invoice_balances_by_jur_cic | B24: Invoice Balance Report | C24: 0 | D24: 0 | E24: 0
A25: CLNT nt_ckt_billed_live_disco_v2 | B25: Facility Circuit Charges Billed Disconnected | C25: 0 | D25: 0 | E25: 0
A26: Count of Invoices not zero Range | B26: Number Of Invoices | C26: 21B_ | D26: 0 | E26: 0
A27: Count Of Invoices not zero Range | B27: Number Of Invoices | C27: 21B_ | D27: 0 | E27: 0
A28: count_of_invoices_not_zero_range | B28: Number Of Invoices | C28: 21B_ | D28: 0 | E28: 0
A29: Deletions Under 5 Report | B29: Deletions Under 5 Report | C29: 0 | D29: 0 | E29: 0
A30: Deletions Under Report | B30: Deletions Under Report | C30: 0 | D30: 0 | E30: 0
A31: Detailed BAN Error Report | B31: Detailed BAN Error Report | C31: 4F_ | D31: 0 | E31: 0
A32: Detailed BAN Error Report - with extra research | B32: Detailed BAN Error Report | C32: 4F_ | D32: 0 | E32: 0
A33: Detailed CLLI Error Report | B33: Detailed CLLI Error Report | C33: 4H_ | D33: 0 | E33: 0
A34: Detailed CLLI Error Report - with extra research | B34: Detailed CLLI Error Report | C34: 4H_ | D34: 0 | E34: 0
A35: Duplicate File Processing Report | B35: Duplicate File Processing Report | C35: 5A_ | D35: 0 | E35: 0
A36: Exception Analysis Report | B36: Exception Analysis Report | C36: 4K_ | D36: 0 | E36: 0
A37: FA BAN Trending Report | B37: Facility BANS Trending Report | C37: 0 | D37: 0 | E37: 0
A38: FA Charges Summary | B38: FA Charges Summary | C38: 0 | D38: 0 | E38: 0
A39: FA Circuit Charges by CIC by CLLI | B39: FA Circuit Charges by CIC by CLLI | C39: 0 | D39: 0 | E39: 0
A40: Facility BANS Trending Report | B40: Facility BANS Trending Report | C40: 12B_ | D40: 12D_ | E40: 12N_
A41: Facility Circuit Charges Billed Disconnected | B41: Facility Circuit Charges Billed Disconnected | C41: 0 | D41: 0 | E41: 0
A42: Factor Change Audit Report | B42: Factor Change Audit Report | C42: 10_ | D42: 0 | E42: 0
A43: Factor Check Report with PVU | B43: Factor Check Report with PVU | C43: 10A_ | D43: 0 | E43: 0
A44: Factor Compare Report | B44: Factor Compare Report | C44: 10B_ | D44: 0 | E44: 0
A45: Factor Matrix Report | B45: Factor Matrix Report | C45: 0 | D45: 0 | E45: 0
A46: Fulfillment Report | B46: Fulfillment Report | C46: 0 | D46: 0 | E46: 0
A47: FUSC Charge By Circuit | B47: FUSC Charge By Circuit | C47: 0 | D47: 0 | E47: 0
A48: GL Extract | B48: GL Extract | C48: 0 | D48: 0 | E48: 0
A49: Invoice Balance | B49: Invoice Balance Report | C49: 0 | D49: 0 | E49: 0
A50: Invoice Balance Report | B50: Invoice Balance Report | C50: 0 | D50: 0 | E50: 0
A51: Invoice Balances by Jur with LPC | B51: Invoice Balances by Jur with LPC | C51: 0 | D51: 0 | E51: 0
A52: Invoice Balances by Jurisdiction | B52: Invoice Balances by Jurisdiction Report | C52: 0 | D52: 0 | E52: 0
A53: Invoice Balances by Jurisdiction Report | B53: Invoice Balances by Jurisdiction Report | C53: 0 | D53: 0 | E53: 0
A54: Invoice Count Range Report (non-zero balance) | B54: Number Of Invoices | C54: 21B_ | D54: 0 | E54: 0
A55: Invoice Count Report - Range | B55: Number Of Invoices | C55: 21B_ | D55: 0 | E55: 0
A56: Invoice Count Report (non-zero balances) | B56: Number Of Invoices | C56: 21B_ | D56: 0 | E56: 0
A57: Invoice Register Report | B57: Invoice Register Report | C57: 0 | D57: 0 | E57: 0
A58: Invoice Trending Report for Export - dir - jur | B58: Invoice Trending Report for Export - dir - jur | C58: 0 | D58: 0 | E58: 0
A59: Invoice Trending Report for Export (qty type dtl) | B59: Invoice Trending Report for Export (qty type dtl) | C59: 0 | D59: 0 | E59: 0
A60: Late Payment Charges | B60: Late Payment Charges | C60: 0 | D60: 0 | E60: 0
A61: Minutes and revenue billed by rate element | B61: Minutes and revenue billed by rate element | C61: 0 | D61: 0 | E61: 0
A62: MMR by Bill Date by Usg Pd by Direction by Prod | B62: MMR by Bill Date by Usg Pd by Direction by Prod | C62: 0 | D62: 0 | E62: 0
A63: MOU Entries Error Report | B63: MOU Entries Error Report | C63: 4L_ | D63: 0 | E63: 0
A64: MSG MOU Rev Export | B64: MMR Report | C64: 0 | D64: 0 | E64: 0
A65: MSG MOU REV Export - New | B65: MMR Report | C65: 0 | D65: 0 | E65: 0
A66: MSG MOU REV with LPC | B66: MSG MOU REV with LPC | C66: 0 | D66: 0 | E66: 0
A67: MSG_MOU_REV_export | B67: MMR Report | C67: 0 | D67: 0 | E67: 0
A68: NECA AS1000 | B68: NECA AS1000 | C68: 0 | D68: 0 | E68: 0
A69: NECA EC1050 | B69: NECA EC1050 | C69: 0 | D69: 0 | E69: 0
A70: OC&C GL Trans by BAN Report | B70: OCC Report | C70: 12P_ | D70: 0 | E70: 0
A71: OC&C Report | B71: OCC Report | C71: 12P_ | D71: 0 | E71: 0
A72: OCC GL Trans by BAN Report - New | B72: OCC Report | C72: 12P_ | D72: 0 | E72: 0
A73: Payment Report | B73: Payment Report | C73: 8_ | D73: 0 | E73: 0
A74: Payment Report - New | B74: Payment Report | C74: 8_ | D74: 0 | E74: 0
A75: Pre-Thresholding Report | B75: Pre-Thresholding Report | C75: 0 | D75: 0 | E75: 0
A76: Rev Analysis by CLLI | B76: Rev Analysis by CLLI | C76: 0 | D76: 0 | E76: 0
A77: Revenue Analysis | B77: Revenue Analysis | C77: 0 | D77: 0 | E77: 0
A78: Revenue Analysis - New | B78: Revenue Analysis | C78: 0 | D78: 0 | E78: 0
A79: SOC Change Audit Report | B79: SOC Change Audit Report | C79: 11_ | D79: 0 | E79: 0
A80: SOC Jurisdiction Report | B80: SOC Jurisdiction Report | C80: 0 | D80: 0 | E80: 0
A81: Sprint MOU Analysis for export | B81: Sprint MOU Analysis for export | C81: 0 | D81: 0 | E81: 0
A82: SW BANS Trending Report (qty type detail) | B82: SW BANS Trending Report | C82: 12C_ | D82: 0 | E82: 0
A83: SW Usage Charges Summary | B83: SW Usage Charges Summary | C83: 0 | D83: 0 | E83: 0
A84: Switch Terminating Intrastate Rev Report for NECA | B84: Switch Terminating Intrastate Rev Report for NECA | C84: 0 | D84: 0 | E84: 0
A85: Switched BANS Trending Report | B85: SW BANS Trending Report | C85: 12B_ | D85: 12M_ | E85: 19W_
A86: Switched BANS Trending Report - New | B86: SW BANS Trending Report | C86: 12B_ | D86: 12M_ | E86: 19W_
A87: Threshold Report by Period | B87: Threshold Report by Period | C87: 0 | D87: 0 | E87: 0
A88: Transaction Summary - bills only | B88: Transaction Summary Report | C88: 0 | D88: 0 | E88: 0
A89: Transaction Summary Report - New | B89: Transaction Summary Report | C89: 0 | D89: 0 | E89: 0
A90: Usage Balancing - Company Totals with Full Detail | B90: Usage Balancing - Company Totals with Full Detail | C90: 11B_ | D90: 0 | E90: 0
A91: Usage Balancing - Company, Ban Totals | B91: Usage Balancing | C91: 6_ | D91: 13_ | E91: 16_
A92: Usage By Day Report | B92: Usage By Day Report | C92: 5D_ | D92: 5E-3months_ | E92: 0
A93: Usage by Day Report - New | B93: Usage By Day Report | C93: 5D_ | D93: 5E-3months_ | E93: 0
A94: Usage Verify by Size Report | B94: Usage Verify by Size Report | C94: 5C_ | D94: 0 | E94: 0
A95: Zero Rated MOU | B95: Zero Rated MOU | C95: 0 | D95: 0 | E95: 0
A96: Facility Billed with Disconnects | B96: Facility Circuit Charges Billed Disconnected | C96: 0 | D96: 0 | E96: 0
A97: 0 | B97: 0 | C97: 0 | D97: 0 | E97: 0
A98: 0 | B98: 0 | C98: 0 | D98: 0 | E98: 0
A99: 0 | B99: 0 | C99: 0 | D99: 0 | E99: 0
A100: 0 | B100: 0 | C100: 0 | D100: 0 | E100: 0
...

Sheet American_Broadband
A1: Before Renaming | B1: After Renaming | C1: Code 1 | D1: Code 2 | E1: Code 3
A2: Accounting Detailed Report | B2: Accounting Detailed Report | C2: 0 | D2: 0 | E2: 0
A3: Accounting Report | B3: Accounting Report | C3: 0 | D3: 0 | E3: 0
A4: Adjustment & OCC Report | B4: Adjustment & OCC Report | C4: 12Q_ | D4: 0 | E4: 0
A5: Adjustment GL Trans by BAN Report | B5: Adjustment Report | C5: 12O_ | D5: 0 | E5: 0
A6: Adjustment GL Trans by BAN Report - New | B6: Adjustment Report | C6: 12O_ | D6: 0 | E6: 0
A7: Adjustments GL Trans by BAN Report | B7: Adjustment Report | C7: 12O_ | D7: 0 | E7: 0
A8: Adjustments Not Posted Report | B8: Adjustments Not Posted Report | C8: 9F_ | D8: 0 | E8: 0
A9: Aged Trial Balance for Export | B9: Aged Trial Balance for Export Report | C9: 0 | D9: 0 | E9: 0
A10: Aged Trial Balance for Export - New | B10: Aged Trial Balance for Export Report | C10: 0 | D10: 0 | E10: 0
A11: Aged Trial Balance_for export | B11: Aged Trial Balance for Export Report | C11: 0 | D11: 0 | E11: 0
A12: Aged trial Balance | B12: Aged trial Balance Report | C12: 0 | D12: 0 | E12: 0
A13: Aged Trial Balance - New | B13: Aged trial Balance Report | C13: 0 | D13: 0 | E13: 0
A14: AUR History Stats | B14: AUR History Stats Report | C14: 4A_ | D14: 0 | E14: 0
A15: AUR History Stats Report | B15: AUR History Stats Report | C15: 4A_ | D15: 0 | E15: 0
A16: BAN List with Active Status and LPC Option | B16: BAN List with Active Status and LPC Option | C16: 0 | D16: 0 | E16: 0
A17: Bill By Period Report | B17: Bill By Period Report | C17: 0 | D17: 0 | E17: 0
A18: Bill Completion Check Report | B18: Bill Completion Check Report | C18: 12A_ | D18: 0 | E18: 0
A19: Billed by Period | B19: Bill By Period Report | C19: 0 | D19: 0 | E19: 0
A20: Billed by Period Report | B20: Bill By Period Report | C20: 0 | D20: 0 | E20: 0
A21: Billed by Period Report - New | B21: Bill By Period Report | C21: 0 | D21: 0 | E21: 0
A22: Billed Msg MOU Rev by BAN by EMR Jurisdiction | B22: Message MOU Revenue by BAN Report | C22: 0 | D22: 0 | E22: 0
A23: Billed Msg MOU Rev by CLLI by EMR Jurisdiction | B23: Message MOU Revenue by CLLI Report | C23: 0 | D23: 0 | E23: 0
A24: CLNT ly_invoice_balances_by_jur_cic | B24: Invoice Balance Report | C24: 0 | D24: 0 | E24: 0
A25: CLNT nt_ckt_billed_live_disco_v2 | B25: Facility Circuit Charges Billed Disconnected | C25: 0 | D25: 0 | E25: 0
A26: Count of Invoices not zero Range | B26: Number Of Invoices | C26: 21B_ | D26: 0 | E26: 0
A27: Count Of Invoices not zero Range | B27: Number Of Invoices | C27: 21B_ | D27: 0 | E27: 0
A28: count_of_invoices_not_zero_range | B28: Number Of Invoices | C28: 21B_ | D28: 0 | E28: 0
A29: Deletions Under 5 Report | B29: Deletions Under 5 Report | C29: 0 | D29: 0 | E29: 0
A30: Deletions Under Report | B30: Deletions Under Report | C30: 0 | D30: 0 | E30: 0
A31: Detailed BAN Error Report | B31: Detailed BAN Error Report | C31: 4F_ | D31: 0 | E31: 0
A32: Detailed BAN Error Report - with extra research | B32: Detailed BAN Error Report | C32: 4F_ | D32: 0 | E32: 0
A33: Detailed CLLI Error Report | B33: Detailed CLLI Error Report | C33: 4H_ | D33: 0 | E33: 0
A34: Detailed CLLI Error Report - with extra research | B34: Detailed CLLI Error Report | C34: 4H_ | D34: 0 | E34: 0
A35: Duplicate File Processing Report | B35: Duplicate File Processing Report | C35: 5A_ | D35: 0 | E35: 0
A36: Exception Analysis Report | B36: Exception Analysis Report | C36: 4K_ | D36: 0 | E36: 0
A37: FA BAN Trending Report | B37: Facility BANS Trending Report | C37: 0 | D37: 0 | E37: 0
A38: FA Charges Summary | B38: FA Charges Summary | C38: 0 | D38: 0 | E38: 0
A39: FA Circuit Charges by CIC by CLLI | B39: FA Circuit Charges by CIC by CLLI | C39: 0 | D39: 0 | E39: 0
A40: Facility BANS Trending Report | B40: Facility BANS Trending Report | C40: 12B_ | D40: 12D_ | E40: 12N_
A41: Facility Circuit Charges Billed Disconnected | B41: Facility Circuit Charges Billed Disconnected | C41: 0 | D41: 0 | E41: 0
A42: Factor Change Audit Report | B42: Factor Change Audit Report | C42: 10_ | D42: 0 | E42: 0
A43: Factor Check Report with PVU | B43: Factor Check Report with PVU | C43: 10A_ | D43: 0 | E43: 0
A44: Factor Compare Report | B44: Factor Compare Report | C44: 10B_ | D44: 0 | E44: 0
A45: Factor Matrix Report | B45: Factor Matrix Report | C45: 0 | D45: 0 | E45: 0
A46: Fulfillment Report | B46: Fulfillment Report | C46: 0 | D46: 0 | E46: 0
A47: FUSC Charge By Circuit | B47: FUSC Charge By Circuit | C47: 0 | D47: 0 | E47: 0
A48: GL Extract | B48: GL Extract | C48: 0 | D48: 0 | E48: 0
A49: Invoice Balance | B49: Invoice Balance Report | C49: 0 | D49: 0 | E49: 0
A50: Invoice Balance Report | B50: Invoice Balance Report | C50: 0 | D50: 0 | E50: 0
A51: Invoice Balances by Jur with LPC | B51: Invoice Balances by Jur with LPC | C51: 0 | D51: 0 | E51: 0
A52: Invoice Balances by Jurisdiction | B52: Invoice Balances by Jurisdiction Report | C52: 0 | D52: 0 | E52: 0
A53: Invoice Balances by Jurisdiction Report | B53: Invoice Balances by Jurisdiction Report | C53: 0 | D53: 0 | E53: 0
A54: Invoice Count Range Report (non-zero balance) | B54: Number Of Invoices | C54: 21B_ | D54: 0 | E54: 0
A55: Invoice Count Report - Range | B55: Number Of Invoices | C55: 21B_ | D55: 0 | E55: 0
A56: Invoice Count Report (non-zero balances) | B56: Number Of Invoices | C56: 21B_ | D56: 0 | E56: 0
A57: Invoice Register Report | B57: Invoice Register Report | C57: 0 | D57: 0 | E57: 0
A58: Invoice Trending Report for Export - dir - jur | B58: Invoice Trending Report for Export - dir - jur | C58: 0 | D58: 0 | E58: 0
A59: Invoice Trending Report for Export (qty type dtl) | B59: Invoice Trending Report for Export (qty type dtl) | C59: 0 | D59: 0 | E59: 0
A60: Late Payment Charges | B60: Late Payment Charges | C60: 0 | D60: 0 | E60: 0
A61: Minutes and revenue billed by rate element | B61: Minutes and revenue billed by rate element | C61: 0 | D61: 0 | E61: 0
A62: MMR by Bill Date by Usg Pd by Direction by Prod | B62: MMR by Bill Date by Usg Pd by Direction by Prod | C62: 0 | D62: 0 | E62: 0
A63: MOU Entries Error Report | B63: MOU Entries Error Report | C63: 4L_ | D63: 0 | E63: 0
A64: MSG MOU Rev Export | B64: MMR Report | C64: 0 | D64: 0 | E64: 0
A65: MSG MOU REV Export - New | B65: MMR Report | C65: 0 | D65: 0 | E65: 0
A66: MSG MOU REV with LPC | B66: MSG MOU REV with LPC | C66: 0 | D66: 0 | E66: 0
A67: MSG_MOU_REV_export | B67: MMR Report | C67: 0 | D67: 0 | E67: 0
A68: NECA AS1000 | B68: NECA AS1000 | C68: 0 | D68: 0 | E68: 0
A69: NECA EC1050 | B69: NECA EC1050 | C69: 0 | D69: 0 | E69: 0
A70: OC&C GL Trans by BAN Report | B70: OCC Report | C70: 12P_ | D70: 0 | E70: 0
A71: OC&C Report | B71: OCC Report | C71: 12P_ | D71: 0 | E71: 0
A72: OCC GL Trans by BAN Report - New | B72: OCC Report | C72: 12P_ | D72: 0 | E72: 0
A73: Payment Report | B73: Payment Report | C73: 8_ | D73: 0 | E73: 0
A74: Payment Report - New | B74: Payment Report | C74: 8_ | D74: 0 | E74: 0
A75: Pre-Thresholding Report | B75: Pre-Thresholding Report | C75: 0 | D75: 0 | E75: 0
A76: Rev Analysis by CLLI | B76: Rev Analysis by CLLI | C76: 0 | D76: 0 | E76: 0
A77: Revenue Analysis | B77: Revenue Analysis | C77: 0 | D77: 0 | E77: 0
A78: Revenue Analysis - New | B78: Revenue Analysis | C78: 0 | D78: 0 | E78: 0
A79: SOC Change Audit Report | B79: SOC Change Audit Report | C79: 11_ | D79: 0 | E79: 0
A80: SOC Jurisdiction Report | B80: SOC Jurisdiction Report | C80: 0 | D80: 0 | E80: 0
A81: Sprint MOU Analysis for export | B81: Sprint MOU Analysis for export | C81: 0 | D81: 0 | E81: 0
A82: SW BANS Trending Report (qty type detail) | B82: SW BANS Trending Report | C82: 12C_ | D82: 0 | E82: 0
A83: SW Usage Charges Summary | B83: SW Usage Charges Summary | C83: 0 | D83: 0 | E83: 0
A84: Switch Terminating Intrastate Rev Report for NECA | B84: Switch Terminating Intrastate Rev Report for NECA | C84: 0 | D84: 0 | E84: 0
A85: Switched BANS Trending Report | B85: SW BANS Trending Report | C85: 12B_ | D85: 12M_ | E85: 19W_
A86: Switched BANS Trending Report - New | B86: SW BANS Trending Report | C86: 12B_ | D86: 12M_ | E86: 19W_
A87: Threshold Report by Period | B87: Threshold Report by Period | C87: 0 | D87: 0 | E87: 0
A88: Transaction Summary - bills only | B88: Transaction Summary Report | C88: 0 | D88: 0 | E88: 0
A89: Transaction Summary Report - New | B89: Transaction Summary Report | C89: 0 | D89: 0 | E89: 0
A90: Usage Balancing - Company Totals with Full Detail | B90: Usage Balancing - Company Totals with Full Detail | C90: 11B_ | D90: 0 | E90: 0
A91: Usage Balancing - Company, Ban Totals | B91: Usage Balancing | C91: 6_ | D91: 13_ | E91: 16_
A92: Usage By Day Report | B92: Usage By Day Report | C92: 5D_ | D92: 5E-3months_ | E92: 0
A93: Usage by Day Report - New | B93: Usage By Day Report | C93: 5D_ | D93: 5E-3months_ | E93: 0
A94: Usage Verify by Size Report | B94: Usage Verify by Size Report | C94: 5C_ | D94: 0 | E94: 0
A95: Zero Rated MOU | B95: Zero Rated MOU | C95: 0 | D95: 0 | E95: 0
A96: Facility Billed with Disconnects | B96: Facility Circuit Charges Billed Disconnected | C96: 0 | D96: 0 | E96: 0
A97: 0 | B97: 0 | C97: 0 | D97: 0 | E97: 0
A98: 0 | B98: 0 | C98: 0 | D98: 0 | E98: 0
A99: 0 | B99: 0 | C99: 0 | D99: 0 | E99: 0
A100: 0 | B100: 0 | C100: 0 | D100: 0 | E100: 0
...

Sheet Specific Names Main
A1: Before Renaming | B1: After Renaming | C1: Code 1 | D1: Code 2 | E1: Code 3
A2: Accounting Detailed Report | B2: Accounting Detailed Report | C2: 0 | D2: 0 | E2: 0
A3: Accounting Report | B3: Accounting Report | C3: 0 | D3: 0 | E3: 0
A4: Adjustment & OCC Report | B4: Adjustment & OCC Report | C4: 12Q_ | D4: 0 | E4: 0
A5: Adjustment GL Trans by BAN Report | B5: Adjustment Report | C5: 12O_ | D5: 0 | E5: 0
A6: Adjustment GL Trans by BAN Report - New | B6: Adjustment Report | C6: 12O_ | D6: 0 | E6: 0
A7: Adjustments GL Trans by BAN Report | B7: Adjustment Report | C7: 12O_ | D7: 0 | E7: 0
A8: Adjustments Not Posted Report | B8: Adjustments Not Posted Report | C8: 9F_ | D8: 0 | E8: 0
A9: Aged Trial Balance for Export | B9: Aged Trial Balance for Export Report | C9: 0 | D9: 0 | E9: 0
A10: Aged Trial Balance for Export - New | B10: Aged Trial Balance for Export Report | C10: 0 | D10: 0 | E10: 0
A11: Aged Trial Balance_for export | B11: Aged Trial Balance for Export Report | C11: 0 | D11: 0 | E11: 0
A12: Aged trial Balance | B12: Aged trial Balance Report | C12: 0 | D12: 0 | E12: 0
A13: Aged Trial Balance - New | B13: Aged trial Balance Report | C13: 0 | D13: 0 | E13: 0
A14: AUR History Stats | B14: AUR History Stats Report | C14: 4A_ | D14: 0 | E14: 0
A15: AUR History Stats Report | B15: AUR History Stats Report | C15: 4A_ | D15: 0 | E15: 0
A16: BAN List with Active Status and LPC Option | B16: BAN List with Active Status and LPC Option | C16: 0 | D16: 0 | E16: 0
A17: Bill By Period Report | B17: Bill By Period Report | C17: 0 | D17: 0 | E17: 0
A18: Bill Completion Check Report | B18: Bill Completion Check Report | C18: 12A_ | D18: 0 | E18: 0
A19: Billed by Period | B19: Bill By Period Report | C19: 0 | D19: 0 | E19: 0
A20: Billed by Period Report | B20: Bill By Period Report | C20: 0 | D20: 0 | E20: 0
A21: Billed by Period Report - New | B21: Bill By Period Report | C21: 0 | D21: 0 | E21: 0
A22: Billed Msg MOU Rev by BAN by EMR Jurisdiction | B22: Message MOU Revenue by BAN Report | C22: 0 | D22: 0 | E22: 0
A23: Billed Msg MOU Rev by CLLI by EMR Jurisdiction | B23: Message MOU Revenue by CLLI Report | C23: 0 | D23: 0 | E23: 0
A24: CLNT ly_invoice_balances_by_jur_cic | B24: Invoice Balance Report | C24: 0 | D24: 0 | E24: 0
A25: CLNT nt_ckt_billed_live_disco_v2 | B25: Facility Circuit Charges Billed Disconnected | C25: 0 | D25: 0 | E25: 0
A26: Count of Invoices not zero Range | B26: Number Of Invoices | C26: 21B_ | D26: 0 | E26: 0
A27: Count Of Invoices not zero Range | B27: Number Of Invoices | C27: 21B_ | D27: 0 | E27: 0
A28: count_of_invoices_not_zero_range | B28: Number Of Invoices | C28: 21B_ | D28: 0 | E28: 0
A29: Deletions Under 5 Report | B29: Deletions Under 5 Report | C29: 0 | D29: 0 | E29: 0
A30: Deletions Under Report | B30: Deletions Under Report | C30: 0 | D30: 0 | E30: 0
A31: Detailed BAN Error Report | B31: Detailed BAN Error Report | C31: 4F_ | D31: 0 | E31: 0
A32: Detailed BAN Error Report - with extra research | B32: Detailed BAN Error Report | C32: 4F_ | D32: 0 | E32: 0
A33: Detailed CLLI Error Report | B33: Detailed CLLI Error Report | C33: 4H_ | D33: 0 | E33: 0
A34: Detailed CLLI Error Report - with extra research | B34: Detailed CLLI Error Report | C34: 4H_ | D34: 0 | E34: 0
A35: Duplicate File Processing Report | B35: Duplicate File Processing Report | C35: 5A_ | D35: 0 | E35: 0
A36: Exception Analysis Report | B36: Exception Analysis Report | C36: 4K_ | D36: 0 | E36: 0
A37: FA BAN Trending Report | B37: Facility BANS Trending Report | C37: 0 | D37: 0 | E37: 0
A38: FA Charges Summary | B38: FA Charges Summary | C38: 0 | D38: 0 | E38: 0
A39: FA Circuit Charges by CIC by CLLI | B39: FA Circuit Charges by CIC by CLLI | C39: 0 | D39: 0 | E39: 0
A40: Facility BANS Trending Report | B40: Facility BANS Trending Report | C40: 12B_ | D40: 12D_ | E40: 12N_
A41: Facility Circuit Charges Billed Disconnected | B41: Facility Circuit Charges Billed Disconnected | C41: 0 | D41: 0 | E41: 0
A42: Factor Change Audit Report | B42: Factor Change Audit Report | C42: 10_ | D42: 0 | E42: 0
A43: Factor Check Report with PVU | B43: Factor Check Report with PVU | C43: 10A_ | D43: 0 | E43: 0
A44: Factor Compare Report | B44: Factor Compare Report | C44: 10B_ | D44: 0 | E44: 0
A45: Factor Matrix Report | B45: Factor Matrix Report | C45: 0 | D45: 0 | E45: 0
A46: Fulfillment Report | B46: Fulfillment Report | C46: 0 | D46: 0 | E46: 0
A47: FUSC Charge By Circuit | B47: FUSC Charge By Circuit | C47: 0 | D47: 0 | E47: 0
A48: GL Extract | B48: GL Extract | C48: 0 | D48: 0 | E48: 0
A49: Invoice Balance | B49: Invoice Balance Report | C49: 0 | D49: 0 | E49: 0
A50: Invoice Balance Report | B50: Invoice Balance Report | C50: 0 | D50: 0 | E50: 0
A51: Invoice Balances by Jur with LPC | B51: Invoice Balances by Jur with LPC | C51: 0 | D51: 0 | E51: 0
A52: Invoice Balances by Jurisdiction | B52: Invoice Balances by Jurisdiction Report | C52: 0 | D52: 0 | E52: 0
A53: Invoice Balances by Jurisdiction Report | B53: Invoice Balances by Jurisdiction Report | C53: 0 | D53: 0 | E53: 0
A54: Invoice Count Range Report (non-zero balance) | B54: Number Of Invoices | C54: 21B_ | D54: 0 | E54: 0
A55: Invoice Count Report - Range | B55: Number Of Invoices | C55: 21B_ | D55: 0 | E55: 0
A56: Invoice Count Report (non-zero balances) | B56: Number Of Invoices | C56: 21B_ | D56: 0 | E56: 0
A57: Invoice Register Report | B57: Invoice Register Report | C57: 0 | D57: 0 | E57: 0
A58: Invoice Trending Report for Export - dir - jur | B58: Invoice Trending Report for Export - dir - jur | C58: 0 | D58: 0 | E58: 0
A59: Invoice Trending Report for Export (qty type dtl) | B59: Invoice Trending Report for Export (qty type dtl) | C59: 0 | D59: 0 | E59: 0
A60: Late Payment Charges | B60: Late Payment Charges | C60: 0 | D60: 0 | E60: 0
A61: Minutes and revenue billed by rate element | B61: Minutes and revenue billed by rate element | C61: 0 | D61: 0 | E61: 0
A62: MMR by Bill Date by Usg Pd by Direction by Prod | B62: MMR by Bill Date by Usg Pd by Direction by Prod | C62: 0 | D62: 0 | E62: 0
A63: MOU Entries Error Report | B63: MOU Entries Error Report | C63: 4L_ | D63: 0 | E63: 0
A64: MSG MOU Rev Export | B64: MMR Report | C64: 0 | D64: 0 | E64: 0
A65: MSG MOU REV Export - New | B65: MMR Report | C65: 0 | D65: 0 | E65: 0
A66: MSG MOU REV with LPC | B66: MSG MOU REV with LPC | C66: 0 | D66: 0 | E66: 0
A67: MSG_MOU_REV_export | B67: MMR Report | C67: 0 | D67: 0 | E67: 0
A68: NECA AS1000 | B68: NECA AS1000 | C68: 0 | D68: 0 | E68: 0
A69: NECA EC1050 | B69: NECA EC1050 | C69: 0 | D69: 0 | E69: 0
A70: OC&C GL Trans by BAN Report | B70: OCC Report | C70: 12P_ | D70: 0 | E70: 0
A71: OC&C Report | B71: OCC Report | C71: 12P_ | D71: 0 | E71: 0
A72: OCC GL Trans by BAN Report - New | B72: OCC Report | C72: 12P_ | D72: 0 | E72: 0
A73: Payment Report | B73: Payment Report | C73: 8_ | D73: 0 | E73: 0
A74: Payment Report - New | B74: Payment Report | C74: 8_ | D74: 0 | E74: 0
A75: Pre-Thresholding Report | B75: Pre-Thresholding Report | C75: 0 | D75: 0 | E75: 0
A76: Rev Analysis by CLLI | B76: Rev Analysis by CLLI | C76: 0 | D76: 0 | E76: 0
A77: Revenue Analysis | B77: Revenue Analysis | C77: 0 | D77: 0 | E77: 0
A78: Revenue Analysis - New | B78: Revenue Analysis | C78: 0 | D78: 0 | E78: 0
A79: SOC Change Audit Report | B79: SOC Change Audit Report | C79: 11_ | D79: 0 | E79: 0
A80: SOC Jurisdiction Report | B80: SOC Jurisdiction Report | C80: 0 | D80: 0 | E80: 0
A81: Sprint MOU Analysis for export | B81: Sprint MOU Analysis for export | C81: 0 | D81: 0 | E81: 0
A82: SW BANS Trending Report (qty type detail) | B82: SW BANS Trending Report | C82: 12C_ | D82: 0 | E82: 0
A83: SW Usage Charges Summary | B83: SW Usage Charges Summary | C83: 0 | D83: 0 | E83: 0
A84: Switch Terminating Intrastate Rev Report for NECA | B84: Switch Terminating Intrastate Rev Report for NECA | C84: 0 | D84: 0 | E84: 0
A85: Switched BANS Trending Report | B85: SW BANS Trending Report | C85: 12B_ | D85: 12M_ | E85: 19W_
A86: Switched BANS Trending Report - New | B86: SW BANS Trending Report | C86: 12B_ | D86: 12M_ | E86: 19W_
A87: Threshold Report by Period | B87: Threshold Report by Period | C87: 0 | D87: 0 | E87: 0
A88: Transaction Summary - bills only | B88: Transaction Summary Report | C88: 0 | D88: 0 | E88: 0
A89: Transaction Summary Report - New | B89: Transaction Summary Report | C89: 0 | D89: 0 | E89: 0
A90: Usage Balancing - Company Totals with Full Detail | B90: Usage Balancing - Company Totals with Full Detail | C90: 11B_ | D90: 0 | E90: 0
A91: Usage Balancing - Company, Ban Totals | B91: Usage Balancing | C91: 6_ | D91: 13_ | E91: 16_
A92: Usage By Day Report | B92: Usage By Day Report | C92: 5D_ | D92: 5E-3months_ | E92: 0
A93: Usage by Day Report - New | B93: Usage By Day Report | C93: 5D_ | D93: 5E-3months_ | E93: 0
A94: Usage Verify by Size Report | B94: Usage Verify by Size Report | C94: 5C_ | D94: 0 | E94: 0
A95: Zero Rated MOU | B95: Zero Rated MOU | C95: 0 | D95: 0 | E95: 0
A96: Facility Billed with Disconnects | B96: Facility Circuit Charges Billed Disconnected | C96: 0 | D96: 0 | E96: 0

Sheet MTA
A1: Before Renaming | B1: After Renaming | C1: Code 1 | D1: Code 2 | E1: Code 3
A2: Accounting Detailed Report | B2: Accounting Detailed Report | C2: 0 | D2: 0 | E2: 0
A3: Accounting Report | B3: Accounting Report | C3: 0 | D3: 0 | E3: 0
A4: Adjustment & OCC Report | B4: Adjustment & OCC Report | C4: 12Q_ | D4: 0 | E4: 0
A5: Adjustment GL Trans by BAN Report | B5: Adjustment Report | C5: 12O_ | D5: 0 | E5: 0
A6: Adjustment GL Trans by BAN Report - New | B6: Adjustment Report | C6: 12O_ | D6: 0 | E6: 0
A7: Adjustments GL Trans by BAN Report | B7: Adjustment Report | C7: 12O_ | D7: 0 | E7: 0
A8: Adjustments Not Posted Report | B8: Adjustments Not Posted Report | C8: 9F_ | D8: 0 | E8: 0
A9: Aged Trial Balance for Export | B9: Aged Trial Balance for Export Report | C9: 0 | D9: 0 | E9: 0
A10: Aged Trial Balance for Export - New | B10: Aged Trial Balance for Export Report | C10: 0 | D10: 0 | E10: 0
A11: Aged Trial Balance_for export | B11: Aged Trial Balance for Export Report | C11: 0 | D11: 0 | E11: 0
A12: Aged trial Balance | B12: Aged trial Balance Report | C12: 0 | D12: 0 | E12: 0
A13: Aged Trial Balance - New | B13: Aged trial Balance Report | C13: 0 | D13: 0 | E13: 0
A14: AUR History Stats | B14: AUR History Stats Report | C14: 4A_ | D14: 0 | E14: 0
A15: AUR History Stats Report | B15: AUR History Stats Report | C15: 4A_ | D15: 0 | E15: 0
A16: BAN List with Active Status and LPC Option | B16: BAN List with Active Status and LPC Option | C16: 0 | D16: 0 | E16: 0
A17: Bill By Period Report | B17: Bill By Period Report | C17: 0 | D17: 0 | E17: 0
A18: Bill Completion Check Report | B18: Bill Completion Check Report | C18: 12A_ | D18: 0 | E18: 0
A19: Billed by Period | B19: Bill By Period Report | C19: 0 | D19: 0 | E19: 0
A20: Billed by Period Report | B20: Bill By Period Report | C20: 0 | D20: 0 | E20: 0
A21: Billed by Period Report - New | B21: Bill By Period Report | C21: 0 | D21: 0 | E21: 0
A22: Billed Msg MOU Rev by BAN by EMR Jurisdiction | B22: Message MOU Revenue by BAN Report | C22: 0 | D22: 0 | E22: 0
A23: Billed Msg MOU Rev by CLLI by EMR Jurisdiction | B23: Message MOU Revenue by CLLI Report | C23: 0 | D23: 0 | E23: 0
A24: CLNT ly_invoice_balances_by_jur_cic | B24: Invoice Balance Report | C24: 0 | D24: 0 | E24: 0
A25: CLNT nt_ckt_billed_live_disco_v2 | B25: Facility Circuit Charges Billed Disconnected | C25: 0 | D25: 0 | E25: 0
A26: Count of Invoices not zero Range | B26: Number Of Invoices | C26: 21B_ | D26: 0 | E26: 0
A27: Count Of Invoices not zero Range | B27: Number Of Invoices | C27: 21B_ | D27: 0 | E27: 0
A28: count_of_invoices_not_zero_range | B28: Number Of Invoices | C28: 21B_ | D28: 0 | E28: 0
A29: Deletions Under 5 Report | B29: Deletions Under 5 Report | C29: 0 | D29: 0 | E29: 0
A30: Deletions Under Report | B30: Deletions Under Report | C30: 0 | D30: 0 | E30: 0
A31: Detailed BAN Error Report | B31: Detailed BAN Error Report | C31: 4F_ | D31: 0 | E31: 0
A32: Detailed BAN Error Report - with extra research | B32: Detailed BAN Error Report | C32: 4F_ | D32: 0 | E32: 0
A33: Detailed CLLI Error Report | B33: Detailed CLLI Error Report | C33: 4H_ | D33: 0 | E33: 0
A34: Detailed CLLI Error Report - with extra research | B34: Detailed CLLI Error Report | C34: 4H_ | D34: 0 | E34: 0
A35: Duplicate File Processing Report | B35: Duplicate File Processing Report | C35: 5A_ | D35: 0 | E35: 0
A36: Exception Analysis Report | B36: Exception Analysis Report | C36: 4K_ | D36: 0 | E36: 0
A37: FA BAN Trending Report | B37: Facility BANS Trending Report | C37: 0 | D37: 0 | E37: 0
A38: FA Charges Summary | B38: FA Charges Summary | C38: 0 | D38: 0 | E38: 0
A39: FA Circuit Charges by CIC by CLLI | B39: FA Circuit Charges by CIC by CLLI | C39: 0 | D39: 0 | E39: 0
A40: Facility BANS Trending Report | B40: Facility BANS Trending Report | C40: 12B_ | D40: 12D_ | E40: 12N_
A41: Facility Circuit Charges Billed Disconnected | B41: Facility Circuit Charges Billed Disconnected | C41: 0 | D41: 0 | E41: 0
A42: Factor Change Audit Report | B42: Factor Change Audit Report | C42: 10_ | D42: 0 | E42: 0
A43: Factor Check Report with PVU | B43: Factor Check Report with PVU | C43: 10A_ | D43: 0 | E43: 0
A44: Factor Compare Report | B44: Factor Compare Report | C44: 10B_ | D44: 0 | E44: 0
A45: Factor Matrix Report | B45: Factor Matrix Report | C45: 0 | D45: 0 | E45: 0
A46: Fulfillment Report | B46: Fulfillment Report | C46: 0 | D46: 0 | E46: 0
A47: FUSC Charge By Circuit | B47: FUSC Charge By Circuit | C47: 0 | D47: 0 | E47: 0
A48: GL Extract | B48: GL Extract | C48: 0 | D48: 0 | E48: 0
A49: Invoice Balance | B49: Invoice Balance Report | C49: 0 | D49: 0 | E49: 0
A50: Invoice Balance Report | B50: Invoice Balance Report | C50: 0 | D50: 0 | E50: 0
A51: Invoice Balances by Jur with LPC | B51: Invoice Balances by Jur with LPC | C51: 0 | D51: 0 | E51: 0
A52: Invoice Balances by Jurisdiction | B52: Invoice Balances by Jurisdiction Report | C52: 0 | D52: 0 | E52: 0
A53: Invoice Balances by Jurisdiction Report | B53: Invoice Balances by Jurisdiction Report | C53: 0 | D53: 0 | E53: 0
A54: Invoice Count Range Report (non-zero balance) | B54: Number Of Invoices | C54: 21B_ | D54: 0 | E54: 0
A55: Invoice Count Report - Range | B55: Number Of Invoices | C55: 21B_ | D55: 0 | E55: 0
A56: Invoice Count Report (non-zero balances) | B56: Number Of Invoices | C56: 21B_ | D56: 0 | E56: 0
A57: Invoice Register Report | B57: Invoice Register Report | C57: 0 | D57: 0 | E57: 0
A58: Invoice Trending Report for Export - dir - jur | B58: Invoice Trending Report for Export - dir - jur | C58: 0 | D58: 0 | E58: 0
A59: Invoice Trending Report for Export (qty type dtl) | B59: Invoice Trending Report for Export (qty type dtl) | C59: 0 | D59: 0 | E59: 0
A60: Late Payment Charges | B60: Late Payment Charges | C60: 0 | D60: 0 | E60: 0
A61: Minutes and revenue billed by rate element | B61: Minutes and revenue billed by rate element | C61: 0 | D61: 0 | E61: 0
A62: MMR by Bill Date by Usg Pd by Direction by Prod | B62: MMR by Bill Date by Usg Pd by Direction by Prod | C62: 0 | D62: 0 | E62: 0
A63: MOU Entries Error Report | B63: MOU Entries Error Report | C63: 4L_ | D63: 0 | E63: 0
A64: MSG MOU Rev Export | B64: MMR Report | C64: 0 | D64: 0 | E64: 0
A65: MSG MOU REV Export - New | B65: MMR Report | C65: 0 | D65: 0 | E65: 0
A66: MSG MOU REV with LPC | B66: MSG MOU REV with LPC | C66: 0 | D66: 0 | E66: 0
A67: MSG_MOU_REV_export | B67: MMR Report | C67: 0 | D67: 0 | E67: 0
A68: NECA AS1000 | B68: NECA AS1000 | C68: 0 | D68: 0 | E68: 0
A69: NECA EC1050 | B69: NECA EC1050 | C69: 0 | D69: 0 | E69: 0
A70: OC&C GL Trans by BAN Report | B70: OCC Report | C70: 12P_ | D70: 0 | E70: 0
A71: OC&C Report | B71: OCC Report | C71: 12P_ | D71: 0 | E71: 0
A72: OCC GL Trans by BAN Report - New | B72: OCC Report | C72: 12P_ | D72: 0 | E72: 0
A73: Payment Report | B73: Payment Report | C73: 8_ | D73: 0 | E73: 0
A74: Payment Report - New | B74: Payment Report | C74: 8_ | D74: 0 | E74: 0
A75: Pre-Thresholding Report | B75: Pre-Thresholding Report | C75: 0 | D75: 0 | E75: 0
A76: Rev Analysis by CLLI | B76: Rev Analysis by CLLI | C76: 0 | D76: 0 | E76: 0
A77: Revenue Analysis | B77: Revenue Analysis | C77: 0 | D77: 0 | E77: 0
A78: Revenue Analysis - New | B78: Revenue Analysis | C78: 0 | D78: 0 | E78: 0
A79: SOC Change Audit Report | B79: SOC Change Audit Report | C79: 11_ | D79: 0 | E79: 0
A80: SOC Jurisdiction Report | B80: SOC Jurisdiction Report | C80: 0 | D80: 0 | E80: 0
A81: Sprint MOU Analysis for export | B81: Sprint MOU Analysis for export | C81: 0 | D81: 0 | E81: 0
A82: SW BANS Trending Report (qty type detail) | B82: SW BANS Trending Report | C82: 12C_ | D82: 0 | E82: 0
A83: SW Usage Charges Summary | B83: SW Usage Charges Summary | C83: 0 | D83: 0 | E83: 0
A84: Switch Terminating Intrastate Rev Report for NECA | B84: Switch Terminating Intrastate Rev Report for NECA | C84: 0 | D84: 0 | E84: 0
A85: Switched BANS Trending Report | B85: SW BANS Trending Report | C85: 12B_ | D85: 12M_ | E85: 19W_
A86: Switched BANS Trending Report - New | B86: SW BANS Trending Report | C86: 12B_ | D86: 12M_ | E86: 19W_
A87: Threshold Report by Period | B87: Threshold Report by Period | C87: 0 | D87: 0 | E87: 0
A88: Transaction Summary - bills only | B88: Transaction Summary Report | C88: 0 | D88: 0 | E88: 0
A89: Transaction Summary Report - New | B89: Transaction Summary Report | C89: 0 | D89: 0 | E89: 0
A90: Usage Balancing - Company Totals with Full Detail | B90: Usage Balancing - Company Totals with Full Detail | C90: 11B_ | D90: 0 | E90: 0
A91: Usage Balancing - Company, Ban Totals | B91: Usage Balancing | C91: 6_ | D91: 13_ | E91: 0
A92: Usage By Day Report | B92: Usage By Day Report | C92: 5D_ | D92: 5E-3months_ | E92: 0
A93: Usage by Day Report - New | B93: Usage By Day Report | C93: 5D_ | D93: 5E-3months_ | E93: 0
A94: Usage Verify by Size Report | B94: Usage Verify by Size Report | C94: 5C_ | D94: 0 | E94: 0
A95: Zero Rated MOU | B95: Zero Rated MOU | C95: 0 | D95: 0 | E95: 0
A96: Facility Billed with Disconnects | B96: Facility Circuit Charges Billed Disconnected | C96: 0 | D96: 0 | E96: 0
A97: 0 | B97: 0 | C97: 0 | D97: 0 | E97: 0
A98: 0 | B98: 0 | C98: 0 | D98: 0 | E98: 0
A99: 0 | B99: 0 | C99: 0 | D99: 0 | E99: 0
A100: 0 | B100: 0 | C100: 0 | D100: 0 | E100: 0
...

Sheet ONVOY
A1: Before Renaming | B1: After Renaming | C1: Code 1 | D1: Code 2 | E1: Code 3
A2: Accounting Detailed Report | B2: Accounting Detailed Report | C2: 0 | D2: 0 | E2: 0
A3: Accounting Report | B3: Accounting Report | C3: 0 | D3: 0 | E3: 0
A4: Adjustment & OCC Report | B4: Adjustment & OCC Report | C4: 12Q_ | D4: 0 | E4: 0
A5: Adjustment GL Trans by BAN Report | B5: Adjustment Report | C5: 12O_ | D5: 0 | E5: 0
A6: Adjustment GL Trans by BAN Report - New | B6: Adjustment Report | C6: 12O_ | D6: 0 | E6: 0
A7: Adjustments GL Trans by BAN Report | B7: Adjustment Report | C7: 12O_ | D7: 0 | E7: 0
A8: Adjustments Not Posted Report | B8: Adjustments Not Posted Report | C8: 9F_ | D8: 0 | E8: 0
A9: Aged Trial Balance for Export | B9: Aged Trial Balance for Export Report | C9: 0 | D9: 0 | E9: 0
A10: Aged Trial Balance for Export - New | B10: Aged Trial Balance for Export Report | C10: 0 | D10: 0 | E10: 0
A11: Aged Trial Balance_for export | B11: Aged Trial Balance for Export Report | C11: 13B_ | D11: 0 | E11: 0
A12: Aged trial Balance | B12: Aged trial Balance Report | C12: 13B_ | D12: 0 | E12: 0
A13: Aged Trial Balance - New | B13: Aged trial Balance Report | C13: 13B_ | D13: 0 | E13: 0
A14: AUR History Stats | B14: AUR History Stats Report | C14: 4A_ | D14: 0 | E14: 0
A15: AUR History Stats Report | B15: AUR History Stats Report | C15: 4A_ | D15: 0 | E15: 0
A16: BAN List with Active Status and LPC Option | B16: BAN List with Active Status and LPC Option | C16: 0 | D16: 0 | E16: 0
A17: Bill By Period Report | B17: Bill By Period Report | C17: 0 | D17: 0 | E17: 0
A18: Bill Completion Check Report | B18: Bill Completion Check Report | C18: 12A_ | D18: 0 | E18: 0
A19: Billed by Period | B19: Bill By Period Report | C19: 0 | D19: 0 | E19: 0
A20: Billed by Period Report | B20: Bill By Period Report | C20: 0 | D20: 0 | E20: 0
A21: Billed by Period Report - New | B21: Bill By Period Report | C21: 0 | D21: 0 | E21: 0
A22: Billed Msg MOU Rev by BAN by EMR Jurisdiction | B22: Message MOU Revenue by BAN Report | C22: 13C_ | D22: 0 | E22: 0
A23: Billed Msg MOU Rev by CLLI by EMR Jurisdiction | B23: Message MOU Revenue by CLLI Report | C23: 0 | D23: 0 | E23: 0
A24: CLNT ly_invoice_balances_by_jur_cic | B24: Invoice Balance Report | C24: 0 | D24: 0 | E24: 0
A25: CLNT nt_ckt_billed_live_disco_v2 | B25: Facility Circuit Charges Billed Disconnected | C25: 0 | D25: 0 | E25: 0
A26: Count of Invoices not zero Range | B26: Number Of Invoices | C26: 21B_ | D26: 0 | E26: 0
A27: Count Of Invoices not zero Range | B27: Number Of Invoices | C27: 21B_ | D27: 0 | E27: 0
A28: count_of_invoices_not_zero_range | B28: Number Of Invoices | C28: 21B_ | D28: 0 | E28: 0
A29: Deletions Under 5 Report | B29: Deletions Under 5 Report | C29: 0 | D29: 0 | E29: 0
A30: Deletions Under Report | B30: Deletions Under Report | C30: 0 | D30: 0 | E30: 0
A31: Detailed BAN Error Report | B31: Detailed BAN Error Report | C31: 4F_ | D31: 0 | E31: 0
A32: Detailed BAN Error Report - with extra research | B32: Detailed BAN Error Report | C32: 4F_ | D32: 0 | E32: 0
A33: Detailed CLLI Error Report | B33: Detailed CLLI Error Report | C33: 4H_ | D33: 0 | E33: 0
A34: Detailed CLLI Error Report - with extra research | B34: Detailed CLLI Error Report | C34: 4H_ | D34: 0 | E34: 0
A35: Duplicate File Processing Report | B35: Duplicate File Processing Report | C35: 5A_ | D35: 0 | E35: 0
A36: Exception Analysis Report | B36: Exception Analysis Report | C36: 4K_ | D36: 0 | E36: 0
A37: FA BAN Trending Report | B37: Facility BANS Trending Report | C37: 0 | D37: 0 | E37: 0
A38: FA Charges Summary | B38: FA Charges Summary | C38: 0 | D38: 0 | E38: 0
A39: FA Circuit Charges by CIC by CLLI | B39: FA Circuit Charges by CIC by CLLI | C39: 0 | D39: 0 | E39: 0
A40: Facility BANS Trending Report | B40: Facility BANS Trending Report | C40: 12B_ | D40: 12D_ | E40: 12N_
A41: Facility Circuit Charges Billed Disconnected | B41: Facility Circuit Charges Billed Disconnected | C41: 0 | D41: 0 | E41: 0
A42: Factor Change Audit Report | B42: Factor Change Audit Report | C42: 10_ | D42: 0 | E42: 0
A43: Factor Check Report with PVU | B43: Factor Check Report with PVU | C43: 10A_ | D43: 0 | E43: 0
A44: Factor Compare Report | B44: Factor Compare Report | C44: 10B_ | D44: 0 | E44: 0
A45: Factor Matrix Report | B45: Factor Matrix Report | C45: 0 | D45: 0 | E45: 0
A46: Fulfillment Report | B46: Fulfillment Report | C46: 0 | D46: 0 | E46: 0
A47: FUSC Charge By Circuit | B47: FUSC Charge By Circuit | C47: 0 | D47: 0 | E47: 0
A48: GL Extract | B48: GL Extract | C48: 0 | D48: 0 | E48: 0
A49: Invoice Balance | B49: Invoice Balance Report | C49: 0 | D49: 0 | E49: 0
A50: Invoice Balance Report | B50: Invoice Balance Report | C50: 0 | D50: 0 | E50: 0
A51: Invoice Balances by Jur with LPC | B51: Invoice Balances by Jur with LPC | C51: 0 | D51: 0 | E51: 0
A52: Invoice Balances by Jurisdiction | B52: Invoice Balances by Jurisdiction Report | C52: 0 | D52: 0 | E52: 0
A53: Invoice Balances by Jurisdiction Report | B53: Invoice Balances by Jurisdiction Report | C53: 0 | D53: 0 | E53: 0
A54: Invoice Count Range Report (non-zero balance) | B54: Number Of Invoices | C54: 21B_ | D54: 0 | E54: 0
A55: Invoice Count Report - Range | B55: Number Of Invoices | C55: 21B_ | D55: 0 | E55: 0
A56: Invoice Count Report (non-zero balances) | B56: Number Of Invoices | C56: 21B_ | D56: 0 | E56: 0
A57: Invoice Register Report | B57: Invoice Register Report | C57: 0 | D57: 0 | E57: 0
A58: Invoice Trending Report for Export - dir - jur | B58: Invoice Trending Report for Export - dir - jur | C58: 0 | D58: 0 | E58: 0
A59: Invoice Trending Report for Export (qty type dtl) | B59: Invoice Trending Report for Export (qty type dtl) | C59: 0 | D59: 0 | E59: 0
A60: Late Payment Charges | B60: Late Payment Charges | C60: 0 | D60: 0 | E60: 0
A61: Minutes and revenue billed by rate element | B61: Minutes and revenue billed by rate element | C61: 0 | D61: 0 | E61: 0
A62: MMR by Bill Date by Usg Pd by Direction by Prod | B62: MMR by Bill Date by Usg Pd by Direction by Prod | C62: 0 | D62: 0 | E62: 0
A63: MOU Entries Error Report | B63: MOU Entries Error Report | C63: 4L_ | D63: 0 | E63: 0
A64: MSG MOU Rev Export | B64: MMR Report | C64: 0 | D64: 0 | E64: 0
A65: MSG MOU REV Export - New | B65: MMR Report | C65: 0 | D65: 0 | E65: 0
A66: MSG MOU REV with LPC | B66: MSG MOU REV with LPC | C66: 0 | D66: 0 | E66: 0
A67: MSG_MOU_REV_export | B67: MMR Report | C67: 0 | D67: 0 | E67: 0
A68: NECA AS1000 | B68: NECA AS1000 | C68: 0 | D68: 0 | E68: 0
A69: NECA EC1050 | B69: NECA EC1050 | C69: 0 | D69: 0 | E69: 0
A70: OC&C GL Trans by BAN Report | B70: OCC Report | C70: 12P_ | D70: 0 | E70: 0
A71: OC&C Report | B71: OCC Report | C71: 12P_ | D71: 0 | E71: 0
A72: OCC GL Trans by BAN Report - New | B72: OCC Report | C72: 12P_ | D72: 0 | E72: 0
A73: Payment Report | B73: Payment Report | C73: 8_ | D73: 0 | E73: 0
A74: Payment Report - New | B74: Payment Report | C74: 8_ | D74: 0 | E74: 0
A75: Pre-Thresholding Report | B75: Pre-Thresholding Report | C75: 0 | D75: 0 | E75: 0
A76: Rev Analysis by CLLI | B76: Rev Analysis by CLLI | C76: 0 | D76: 0 | E76: 0
A77: Revenue Analysis | B77: Revenue Analysis | C77: 0 | D77: 0 | E77: 0
A78: Revenue Analysis - New | B78: Revenue Analysis | C78: 0 | D78: 0 | E78: 0
A79: SOC Change Audit Report | B79: SOC Change Audit Report | C79: 11_ | D79: 0 | E79: 0
A80: SOC Jurisdiction Report | B80: SOC Jurisdiction Report | C80: 0 | D80: 0 | E80: 0
A81: Sprint MOU Analysis for export | B81: Sprint MOU Analysis for export | C81: 0 | D81: 0 | E81: 0
A82: SW BANS Trending Report (qty type detail) | B82: SW BANS Trending Report | C82: 12C_ | D82: 0 | E82: 0
A83: SW Usage Charges Summary | B83: SW Usage Charges Summary | C83: 0 | D83: 0 | E83: 0
A84: Switch Terminating Intrastate Rev Report for NECA | B84: Switch Terminating Intrastate Rev Report for NECA | C84: 0 | D84: 0 | E84: 0
A85: Switched BANS Trending Report | B85: SW BANS Trending Report | C85: 12B_ | D85: 12M_ | E85: 19W_
A86: Switched BANS Trending Report - New | B86: SW BANS Trending Report | C86: 12B_ | D86: 12M_ | E86: 19W_
A87: Threshold Report by Period | B87: Threshold Report by Period | C87: 0 | D87: 0 | E87: 0
A88: Transaction Summary - bills only | B88: Transaction Summary Report | C88: 13D_ | D88: 0 | E88: 0
A89: Transaction Summary Report - New | B89: Transaction Summary Report | C89: 13D_ | D89: 0 | E89: 0
A90: Usage Balancing - Company Totals with Full Detail | B90: Usage Balancing - Company Totals with Full Detail | C90: 11B_ | D90: 0 | E90: 0
A91: Usage Balancing - Company, Ban Totals | B91: Usage Balancing | C91: 6_ | D91: 13_ | E91: 16_
A92: Usage By Day Report | B92: Usage By Day Report | C92: 5D_ | D92: 5E-3months_ | E92: 0
A93: Usage by Day Report - New | B93: Usage By Day Report | C93: 5D_ | D93: 5E-3months_ | E93: 0
A94: Usage Verify by Size Report | B94: Usage Verify by Size Report | C94: 5C_ | D94: 0 | E94: 0
A95: Zero Rated MOU | B95: Zero Rated MOU | C95: 0 | D95: 0 | E95: 0
A96: Facility Billed with Disconnects | B96: Facility Circuit Charges Billed Disconnected | C96: 0 | D96: 0 | E96: 0
A97: 0 | B97: 0 | C97: 0 | D97: 0 | E97: 0
A98: 0 | B98: 0 | C98: 0 | D98: 0 | E98: 0
A99: 0 | B99: 0 | C99: 0 | D99: 0 | E99: 0
A100: 0 | B100: 0 | C100: 0 | D100: 0 | E100: 0
...

Sheet Peerless_Network
A1: Before Renaming | B1: After Renaming | C1: Code 1 | D1: Code 2 | E1: Code 3
A2: Accounting Detailed Report | B2: Accounting Detailed Report | C2: 0 | D2: 0 | E2: 0
A3: Accounting Report | B3: Accounting Report | C3: 0 | D3: 0 | E3: 0
A4: Adjustment & OCC Report | B4: Adjustment & OCC Report | C4: 12Q_ | D4: 0 | E4: 0
A5: Adjustment GL Trans by BAN Report | B5: Adjustment Report | C5: 12O_ | D5: 0 | E5: 0
A6: Adjustment GL Trans by BAN Report - New | B6: Adjustment Report | C6: 12O_ | D6: 0 | E6: 0
A7: Adjustments GL Trans by BAN Report | B7: Adjustment Report | C7: 12O_ | D7: 0 | E7: 0
A8: Adjustments Not Posted Report | B8: Adjustments Not Posted Report | C8: 9F_ | D8: 0 | E8: 0
A9: Aged Trial Balance for Export | B9: Aged Trial Balance for Export Report | C9: 0 | D9: 0 | E9: 0
A10: Aged Trial Balance for Export - New | B10: Aged Trial Balance for Export Report | C10: 0 | D10: 0 | E10: 0
A11: Aged Trial Balance_for export | B11: Aged Trial Balance for Export Report | C11: 0 | D11: 0 | E11: 0
A12: Aged trial Balance | B12: Aged trial Balance Report | C12: 0 | D12: 0 | E12: 0
A13: Aged Trial Balance - New | B13: Aged trial Balance Report | C13: 0 | D13: 0 | E13: 0
A14: AUR History Stats | B14: AUR History Stats Report | C14: 4A_ | D14: 0 | E14: 0
A15: AUR History Stats Report | B15: AUR History Stats Report | C15: 4A_ | D15: 0 | E15: 0
A16: BAN List with Active Status and LPC Option | B16: BAN List with Active Status and LPC Option | C16: 0 | D16: 0 | E16: 0
A17: Bill By Period Report | B17: Bill By Period Report | C17: 0 | D17: 0 | E17: 0
A18: Bill Completion Check Report | B18: Bill Completion Check Report | C18: 12A_ | D18: 0 | E18: 0
A19: Billed by Period | B19: Bill By Period Report | C19: 0 | D19: 0 | E19: 0
A20: Billed by Period Report | B20: Bill By Period Report | C20: 0 | D20: 0 | E20: 0
A21: Billed by Period Report - New | B21: Bill By Period Report | C21: 0 | D21: 0 | E21: 0
A22: Billed Msg MOU Rev by BAN by EMR Jurisdiction | B22: Message MOU Revenue by BAN Report | C22: 0 | D22: 0 | E22: 0
A23: Billed Msg MOU Rev by CLLI by EMR Jurisdiction | B23: Message MOU Revenue by CLLI Report | C23: 0 | D23: 0 | E23: 0
A24: CLNT ly_invoice_balances_by_jur_cic | B24: Invoice Balance Report | C24: 0 | D24: 0 | E24: 0
A25: CLNT nt_ckt_billed_live_disco_v2 | B25: Facility Circuit Charges Billed Disconnected | C25: 0 | D25: 0 | E25: 0
A26: Count of Invoices not zero Range | B26: Number Of Invoices | C26: 21B_ | D26: 0 | E26: 0
A27: Count Of Invoices not zero Range | B27: Number Of Invoices | C27: 21B_ | D27: 0 | E27: 0
A28: count_of_invoices_not_zero_range | B28: Number Of Invoices | C28: 21B_ | D28: 0 | E28: 0
A29: Deletions Under 5 Report | B29: Deletions Under 5 Report | C29: 0 | D29: 0 | E29: 0
A30: Deletions Under Report | B30: Deletions Under Report | C30: 0 | D30: 0 | E30: 0
A31: Detailed BAN Error Report | B31: Detailed BAN Error Report | C31: 4F_ | D31: 0 | E31: 0
A32: Detailed BAN Error Report - with extra research | B32: Detailed BAN Error Report | C32: 4F_ | D32: 0 | E32: 0
A33: Detailed CLLI Error Report | B33: Detailed CLLI Error Report | C33: 4H_ | D33: 0 | E33: 0
A34: Detailed CLLI Error Report - with extra research | B34: Detailed CLLI Error Report | C34: 4H_ | D34: 0 | E34: 0
A35: Duplicate File Processing Report | B35: Duplicate File Processing Report | C35: 5A_ | D35: 0 | E35: 0
A36: Exception Analysis Report | B36: Exception Analysis Report | C36: 4K_ | D36: 0 | E36: 0
A37: FA BAN Trending Report | B37: Facility BANS Trending Report | C37: 0 | D37: 0 | E37: 0
A38: FA Charges Summary | B38: FA Charges Summary | C38: 0 | D38: 0 | E38: 0
A39: FA Circuit Charges by CIC by CLLI | B39: FA Circuit Charges by CIC by CLLI | C39: 0 | D39: 0 | E39: 0
A40: Facility BANS Trending Report | B40: Facility BANS Trending Report | C40: 12B_ | D40: 12D_ | E40: 12N_
A41: Facility Circuit Charges Billed Disconnected | B41: Facility Circuit Charges Billed Disconnected | C41: 0 | D41: 0 | E41: 0
A42: Factor Change Audit Report | B42: Factor Change Audit Report | C42: 10_ | D42: 0 | E42: 0
A43: Factor Check Report with PVU | B43: Factor Check Report with PVU | C43: 10A_ | D43: 0 | E43: 0
A44: Factor Compare Report | B44: Factor Compare Report | C44: 10B_ | D44: 0 | E44: 0
A45: Factor Matrix Report | B45: Factor Matrix Report | C45: 0 | D45: 0 | E45: 0
A46: Fulfillment Report | B46: Fulfillment Report | C46: 0 | D46: 0 | E46: 0
A47: FUSC Charge By Circuit | B47: FUSC Charge By Circuit | C47: 0 | D47: 0 | E47: 0
A48: GL Extract | B48: GL Extract | C48: 0 | D48: 0 | E48: 0
A49: Invoice Balance | B49: Invoice Balance Report | C49: 0 | D49: 0 | E49: 0
A50: Invoice Balance Report | B50: Invoice Balance Report | C50: 0 | D50: 0 | E50: 0
A51: Invoice Balances by Jur with LPC | B51: Invoice Balances by Jur with LPC | C51: 0 | D51: 0 | E51: 0
A52: Invoice Balances by Jurisdiction | B52: Invoice Balances by Jurisdiction Report | C52: 0 | D52: 0 | E52: 0
A53: Invoice Balances by Jurisdiction Report | B53: Invoice Balances by Jurisdiction Report | C53: 0 | D53: 0 | E53: 0
A54: Invoice Count Range Report (non-zero balance) | B54: Number Of Invoices | C54: 21B_ | D54: 0 | E54: 0
A55: Invoice Count Report - Range | B55: Number Of Invoices | C55: 21B_ | D55: 0 | E55: 0
A56: Invoice Count Report (non-zero balances) | B56: Number Of Invoices | C56: 21B_ | D56: 0 | E56: 0
A57: Invoice Register Report | B57: Invoice Register Report | C57: 0 | D57: 0 | E57: 0
A58: Invoice Trending Report for Export - dir - jur | B58: Invoice Trending Report for Export - dir - jur | C58: 0 | D58: 0 | E58: 0
A59: Invoice Trending Report for Export (qty type dtl) | B59: Invoice Trending Report for Export (qty type dtl) | C59: 0 | D59: 0 | E59: 0
A60: Late Payment Charges | B60: Late Payment Charges | C60: 0 | D60: 0 | E60: 0
A61: Minutes and revenue billed by rate element | B61: Minutes and revenue billed by rate element | C61: 0 | D61: 0 | E61: 0
A62: MMR by Bill Date by Usg Pd by Direction by Prod | B62: MMR by Bill Date by Usg Pd by Direction by Prod | C62: 0 | D62: 0 | E62: 0
A63: MOU Entries Error Report | B63: MOU Entries Error Report | C63: 4L_ | D63: 0 | E63: 0
A64: MSG MOU Rev Export | B64: MMR Report | C64: 0 | D64: 0 | E64: 0
A65: MSG MOU REV Export - New | B65: MMR Report | C65: 0 | D65: 0 | E65: 0
A66: MSG MOU REV with LPC | B66: MSG MOU REV with LPC | C66: 0 | D66: 0 | E66: 0
A67: MSG_MOU_REV_export | B67: MMR Report | C67: 0 | D67: 0 | E67: 0
A68: NECA AS1000 | B68: NECA AS1000 | C68: 0 | D68: 0 | E68: 0
A69: NECA EC1050 | B69: NECA EC1050 | C69: 0 | D69: 0 | E69: 0
A70: OC&C GL Trans by BAN Report | B70: OCC Report | C70: 12P_ | D70: 0 | E70: 0
A71: OC&C Report | B71: OCC Report | C71: 12P_ | D71: 0 | E71: 0
A72: OCC GL Trans by BAN Report - New | B72: OCC Report | C72: 12P_ | D72: 0 | E72: 0
A73: Payment Report | B73: Payment Report | C73: 8_ | D73: 0 | E73: 0
A74: Payment Report - New | B74: Payment Report | C74: 8_ | D74: 0 | E74: 0
A75: Pre-Thresholding Report | B75: Pre-Thresholding Report | C75: 0 | D75: 0 | E75: 0
A76: Rev Analysis by CLLI | B76: Rev Analysis by CLLI | C76: 0 | D76: 0 | E76: 0
A77: Revenue Analysis | B77: Revenue Analysis | C77: 0 | D77: 0 | E77: 0
A78: Revenue Analysis - New | B78: Revenue Analysis | C78: 0 | D78: 0 | E78: 0
A79: SOC Change Audit Report | B79: SOC Change Audit Report | C79: 11_ | D79: 0 | E79: 0
A80: SOC Jurisdiction Report | B80: SOC Jurisdiction Report | C80: 0 | D80: 0 | E80: 0
A81: Sprint MOU Analysis for export | B81: Sprint MOU Analysis for export | C81: 0 | D81: 0 | E81: 0
A82: SW BANS Trending Report (qty type detail) | B82: SW BANS Trending Report | C82: 12C_ | D82: 0 | E82: 0
A83: SW Usage Charges Summary | B83: SW Usage Charges Summary | C83: 0 | D83: 0 | E83: 0
A84: Switch Terminating Intrastate Rev Report for NECA | B84: Switch Terminating Intrastate Rev Report for NECA | C84: 0 | D84: 0 | E84: 0
A85: Switched BANS Trending Report | B85: SW BANS Trending Report | C85: 12B_ | D85: 12M_ | E85: 19W_
A86: Switched BANS Trending Report - New | B86: SW BANS Trending Report | C86: 12B_ | D86: 12M_ | E86: 19W_
A87: Threshold Report by Period | B87: Threshold Report by Period | C87: 0 | D87: 0 | E87: 0
A88: Transaction Summary - bills only | B88: Transaction Summary Report | C88: 0 | D88: 0 | E88: 0
A89: Transaction Summary Report - New | B89: Transaction Summary Report | C89: 0 | D89: 0 | E89: 0
A90: Usage Balancing - Company Totals with Full Detail | B90: Usage Balancing - Company Totals with Full Detail | C90: 11B_ | D90: 0 | E90: 0
A91: Usage Balancing - Company, Ban Totals | B91: Usage Balancing | C91: 6_ | D91: 13_ | E91: 16_
A92: Usage By Day Report | B92: Usage By Day Report | C92: 5D_ | D92: 5E-3months_ | E92: 0
A93: Usage by Day Report - New | B93: Usage By Day Report | C93: 5D_ | D93: 5E-3months_ | E93: 0
A94: Usage Verify by Size Report | B94: Usage Verify by Size Report | C94: 5C_ | D94: 0 | E94: 0
A95: Zero Rated MOU | B95: Zero Rated MOU | C95: 0 | D95: 0 | E95: 0
A96: Facility Billed with Disconnects | B96: Facility Circuit Charges Billed Disconnected | C96: 0 | D96: 0 | E96: 0
A97: 0 | B97: 0 | C97: 0 | D97: 0 | E97: 0
A98: 0 | B98: 0 | C98: 0 | D98: 0 | E98: 0
A99: 0 | B99: 0 | C99: 0 | D99: 0 | E99: 0
A100: 0 | B100: 0 | C100: 0 | D100: 0 | E100: 0
...

Sheet MIEAC
A1: Before Renaming | B1: After Renaming | C1: Code 1 | D1: Code 2 | E1: Code 3
A2: Accounting Detailed Report | B2: Accounting Detailed Report | C2: 0 | D2: 0 | E2: 0
A3: Accounting Report | B3: Accounting Report | C3: 0 | D3: 0 | E3: 0
A4: Adjustment & OCC Report | B4: Adjustment & OCC Report | C4: 12Q_ | D4: 0 | E4: 0
A5: Adjustment GL Trans by BAN Report | B5: Adjustment Report | C5: 12O_ | D5: 0 | E5: 0
A6: Adjustment GL Trans by BAN Report - New | B6: Adjustment Report | C6: 12O_ | D6: 0 | E6: 0
A7: Adjustments GL Trans by BAN Report | B7: Adjustment Report | C7: 12O_ | D7: 0 | E7: 0
A8: Adjustments Not Posted Report | B8: Adjustments Not Posted Report | C8: 9F_ | D8: 0 | E8: 0
A9: Aged Trial Balance for Export | B9: Aged Trial Balance for Export Report | C9: 0 | D9: 0 | E9: 0
A10: Aged Trial Balance for Export - New | B10: Aged Trial Balance for Export Report | C10: 0 | D10: 0 | E10: 0
A11: Aged Trial Balance_for export | B11: Aged Trial Balance for Export Report | C11: 0 | D11: 0 | E11: 0
A12: Aged trial Balance | B12: Aged trial Balance Report | C12: 13B_ | D12: 0 | E12: 0
A13: Aged Trial Balance - New | B13: Aged trial Balance Report | C13: 13B_ | D13: 0 | E13: 0
A14: AUR History Stats | B14: AUR History Stats Report | C14: 4A_ | D14: 0 | E14: 0
A15: AUR History Stats Report | B15: AUR History Stats Report | C15: 4A_ | D15: 0 | E15: 0
A16: BAN List with Active Status and LPC Option | B16: BAN List with Active Status and LPC Option | C16: 0 | D16: 0 | E16: 0
A17: Bill By Period Report | B17: Bill By Period Report | C17: 0 | D17: 0 | E17: 0
A18: Bill Completion Check Report | B18: Bill Completion Check Report | C18: 12A_ | D18: 0 | E18: 0
A19: Billed by Period | B19: Bill By Period Report | C19: 0 | D19: 0 | E19: 0
A20: Billed by Period Report | B20: Bill By Period Report | C20: 0 | D20: 0 | E20: 0
A21: Billed by Period Report - New | B21: Bill By Period Report | C21: 0 | D21: 0 | E21: 0
A22: Billed Msg MOU Rev by BAN by EMR Jurisdiction | B22: Message MOU Revenue by BAN Report | C22: 13_ | D22: 0 | E22: 0
A23: Billed Msg MOU Rev by CLLI by EMR Jurisdiction | B23: Message MOU Revenue by CLLI Report | C23: 0 | D23: 0 | E23: 0
A24: CLNT ly_invoice_balances_by_jur_cic | B24: Invoice Balance Report | C24: 0 | D24: 0 | E24: 0
A25: CLNT nt_ckt_billed_live_disco_v2 | B25: Facility Circuit Charges Billed Disconnected | C25: 0 | D25: 0 | E25: 0
A26: Count of Invoices not zero Range | B26: Number Of Invoices | C26: 21B_ | D26: 0 | E26: 0
A27: Count Of Invoices not zero Range | B27: Number Of Invoices | C27: 21B_ | D27: 0 | E27: 0
A28: count_of_invoices_not_zero_range | B28: Number Of Invoices | C28: 21B_ | D28: 0 | E28: 0
A29: Deletions Under 5 Report | B29: Deletions Under 5 Report | C29: 0 | D29: 0 | E29: 0
A30: Deletions Under Report | B30: Deletions Under Report | C30: 0 | D30: 0 | E30: 0
A31: Detailed BAN Error Report | B31: Detailed BAN Error Report | C31: 4F_ | D31: 0 | E31: 0
A32: Detailed BAN Error Report - with extra research | B32: Detailed BAN Error Report | C32: 4F_ | D32: 0 | E32: 0
A33: Detailed CLLI Error Report | B33: Detailed CLLI Error Report | C33: 4H_ | D33: 0 | E33: 0
A34: Detailed CLLI Error Report - with extra research | B34: Detailed CLLI Error Report | C34: 4H_ | D34: 0 | E34: 0
A35: Duplicate File Processing Report | B35: Duplicate File Processing Report | C35: 5A_ | D35: 0 | E35: 0
A36: Exception Analysis Report | B36: Exception Analysis Report | C36: 4K_ | D36: 0 | E36: 0
A37: FA BAN Trending Report | B37: Facility BANS Trending Report | C37: 0 | D37: 0 | E37: 0
A38: FA Charges Summary | B38: FA Charges Summary | C38: 0 | D38: 0 | E38: 0
A39: FA Circuit Charges by CIC by CLLI | B39: FA Circuit Charges by CIC by CLLI | C39: 0 | D39: 0 | E39: 0
A40: Facility BANS Trending Report | B40: Facility BANS Trending Report | C40: 12B_ | D40: 12D_ | E40: 12N_
A41: Facility Circuit Charges Billed Disconnected | B41: Facility Circuit Charges Billed Disconnected | C41: 0 | D41: 0 | E41: 0
A42: Factor Change Audit Report | B42: Factor Change Audit Report | C42: 10_ | D42: 0 | E42: 0
A43: Factor Check Report with PVU | B43: Factor Check Report with PVU | C43: 10A_ | D43: 0 | E43: 0
A44: Factor Compare Report | B44: Factor Compare Report | C44: 10B_ | D44: 0 | E44: 0
A45: Factor Matrix Report | B45: Factor Matrix Report | C45: 0 | D45: 0 | E45: 0
A46: Fulfillment Report | B46: Fulfillment Report | C46: 0 | D46: 0 | E46: 0
A47: FUSC Charge By Circuit | B47: FUSC Charge By Circuit | C47: 0 | D47: 0 | E47: 0
A48: GL Extract | B48: GL Extract | C48: 0 | D48: 0 | E48: 0
A49: Invoice Balance | B49: Invoice Balance Report | C49: 0 | D49: 0 | E49: 0
A50: Invoice Balance Report | B50: Invoice Balance Report | C50: 0 | D50: 0 | E50: 0
A51: Invoice Balances by Jur with LPC | B51: Invoice Balances by Jur with LPC | C51: 0 | D51: 0 | E51: 0
A52: Invoice Balances by Jurisdiction | B52: Invoice Balances by Jurisdiction Report | C52: 0 | D52: 0 | E52: 0
A53: Invoice Balances by Jurisdiction Report | B53: Invoice Balances by Jurisdiction Report | C53: 0 | D53: 0 | E53: 0
A54: Invoice Count Range Report (non-zero balance) | B54: Number Of Invoices | C54: 21B_ | D54: 0 | E54: 0
A55: Invoice Count Report - Range | B55: Number Of Invoices | C55: 21B_ | D55: 0 | E55: 0
A56: Invoice Count Report (non-zero balances) | B56: Number Of Invoices | C56: 21B_ | D56: 0 | E56: 0
A57: Invoice Register Report | B57: Invoice Register Report | C57: 0 | D57: 0 | E57: 0
A58: Invoice Trending Report for Export - dir - jur | B58: Invoice Trending Report for Export - dir - jur | C58: 0 | D58: 0 | E58: 0
A59: Invoice Trending Report for Export (qty type dtl) | B59: Invoice Trending Report for Export (qty type dtl) | C59: 0 | D59: 0 | E59: 0
A60: Late Payment Charges | B60: Late Payment Charges | C60: 0 | D60: 0 | E60: 0
A61: Minutes and revenue billed by rate element | B61: Minutes and revenue billed by rate element | C61: 0 | D61: 0 | E61: 0
A62: MMR by Bill Date by Usg Pd by Direction by Prod | B62: MMR by Bill Date by Usg Pd by Direction by Prod | C62: 0 | D62: 0 | E62: 0
A63: MOU Entries Error Report | B63: MOU Entries Error Report | C63: 4L_ | D63: 0 | E63: 0
A64: MSG MOU Rev Export | B64: MMR Report | C64: 0 | D64: 0 | E64: 0
A65: MSG MOU REV Export - New | B65: MMR Report | C65: 0 | D65: 0 | E65: 0
A66: MSG MOU REV with LPC | B66: MSG MOU REV with LPC | C66: 0 | D66: 0 | E66: 0
A67: MSG_MOU_REV_export | B67: MMR Report | C67: 0 | D67: 0 | E67: 0
A68: NECA AS1000 | B68: NECA AS1000 | C68: 0 | D68: 0 | E68: 0
A69: NECA EC1050 | B69: NECA EC1050 | C69: 0 | D69: 0 | E69: 0
A70: OC&C GL Trans by BAN Report | B70: OCC Report | C70: 12P_ | D70: 0 | E70: 0
A71: OC&C Report | B71: OCC Report | C71: 12P_ | D71: 0 | E71: 0
A72: OCC GL Trans by BAN Report - New | B72: OCC Report | C72: 12P_ | D72: 0 | E72: 0
A73: Payment Report | B73: Payment Report | C73: 8_ | D73: 0 | E73: 0
A74: Payment Report - New | B74: Payment Report | C74: 8_ | D74: 0 | E74: 0
A75: Pre-Thresholding Report | B75: Pre-Thresholding Report | C75: 0 | D75: 0 | E75: 0
A76: Rev Analysis by CLLI | B76: Rev Analysis by CLLI | C76: 0 | D76: 0 | E76: 0
A77: Revenue Analysis | B77: Revenue Analysis | C77: 0 | D77: 0 | E77: 0
A78: Revenue Analysis - New | B78: Revenue Analysis | C78: 0 | D78: 0 | E78: 0
A79: SOC Change Audit Report | B79: SOC Change Audit Report | C79: 11_ | D79: 0 | E79: 0
A80: SOC Jurisdiction Report | B80: SOC Jurisdiction Report | C80: 0 | D80: 0 | E80: 0
A81: Sprint MOU Analysis for export | B81: Sprint MOU Analysis for export | C81: 0 | D81: 0 | E81: 0
A82: SW BANS Trending Report (qty type detail) | B82: SW BANS Trending Report | C82: 12C_ | D82: 0 | E82: 0
A83: SW Usage Charges Summary | B83: SW Usage Charges Summary | C83: 0 | D83: 0 | E83: 0
A84: Switch Terminating Intrastate Rev Report for NECA | B84: Switch Terminating Intrastate Rev Report for NECA | C84: 0 | D84: 0 | E84: 0
A85: Switched BANS Trending Report | B85: SW BANS Trending Report | C85: 12B_ | D85: 12M_ | E85: 19W_
A86: Switched BANS Trending Report - New | B86: SW BANS Trending Report | C86: 12B_ | D86: 12M_ | E86: 19W_
A87: Threshold Report by Period | B87: Threshold Report by Period | C87: 0 | D87: 0 | E87: 0
A88: Transaction Summary - bills only | B88: Transaction Summary Report | C88: 13D_ | D88: 0 | E88: 0
A89: Transaction Summary Report - New | B89: Transaction Summary Report | C89: 13D_ | D89: 0 | E89: 0
A90: Usage Balancing - Company Totals with Full Detail | B90: Usage Balancing - Company Totals with Full Detail | C90: 11B_ | D90: 0 | E90: 0
A91: Usage Balancing - Company, Ban Totals | B91: Usage Balancing | C91: 6_ | D91: 13_ | E91: 16_
A92: Usage By Day Report | B92: Usage By Day Report | C92: 5D_ | D92: 5E-3months_ | E92: 0
A93: Usage by Day Report - New | B93: Usage By Day Report | C93: 5D_ | D93: 5E-3months_ | E93: 0
A94: Usage Verify by Size Report | B94: Usage Verify by Size Report | C94: 5C_ | D94: 0 | E94: 0
A95: Zero Rated MOU | B95: Zero Rated MOU | C95: 0 | D95: 0 | E95: 0
A96: Facility Billed with Disconnects | B96: Facility Circuit Charges Billed Disconnected | C96: 0 | D96: 0 | E96: 0

Sheet Selectronics
A1: Before Renaming | B1: After Renaming | C1: Code 1 | D1: Code 2 | E1: Code 3
A2: Accounting Detailed Report | B2: Accounting Detailed Report | C2: 0 | D2: 0 | E2: 0
A3: Accounting Report | B3: Accounting Report | C3: 0 | D3: 0 | E3: 0
A4: Adjustment & OCC Report | B4: Adjustment & OCC Report | C4: 12Q_ | D4: 0 | E4: 0
A5: Adjustment GL Trans by BAN Report | B5: Adjustment Report | C5: 12O_ | D5: 0 | E5: 0
A6: Adjustment GL Trans by BAN Report - New | B6: Adjustment Report | C6: 12O_ | D6: 0 | E6: 0
A7: Adjustments GL Trans by BAN Report | B7: Adjustment Report | C7: 12O_ | D7: 0 | E7: 0
A8: Adjustments Not Posted Report | B8: Adjustments Not Posted Report | C8: 9F_ | D8: 0 | E8: 0
A9: Aged Trial Balance for Export | B9: Aged Trial Balance for Export Report | C9: 0 | D9: 0 | E9: 0
A10: Aged Trial Balance for Export - New | B10: Aged Trial Balance for Export Report | C10: 0 | D10: 0 | E10: 0
A11: Aged Trial Balance_for export | B11: Aged Trial Balance for Export Report | C11: 0 | D11: 0 | E11: 0
A12: Aged trial Balance | B12: Aged trial Balance Report | C12: 0 | D12: 0 | E12: 0
A13: Aged Trial Balance - New | B13: Aged trial Balance Report | C13: 0 | D13: 0 | E13: 0
A14: AUR History Stats | B14: AUR History Stats Report | C14: 4A_ | D14: 0 | E14: 0
A15: AUR History Stats Report | B15: AUR History Stats Report | C15: 4A_ | D15: 0 | E15: 0
A16: BAN List with Active Status and LPC Option | B16: BAN List with Active Status and LPC Option | C16: 0 | D16: 0 | E16: 0
A17: Bill By Period Report | B17: Bill By Period Report | C17: 0 | D17: 0 | E17: 0
A18: Bill Completion Check Report | B18: Bill Completion Check Report | C18: 12A_ | D18: 0 | E18: 0
A19: Billed by Period | B19: Bill By Period Report | C19: 0 | D19: 0 | E19: 0
A20: Billed by Period Report | B20: Bill By Period Report | C20: 0 | D20: 0 | E20: 0
A21: Billed by Period Report - New | B21: Bill By Period Report | C21: 0 | D21: 0 | E21: 0
A22: Billed Msg MOU Rev by BAN by EMR Jurisdiction | B22: Message MOU Revenue by BAN Report | C22: 0 | D22: 0 | E22: 0
A23: Billed Msg MOU Rev by CLLI by EMR Jurisdiction | B23: Message MOU Revenue by CLLI Report | C23: 0 | D23: 0 | E23: 0
A24: CLNT ly_invoice_balances_by_jur_cic | B24: Invoice Balance Report | C24: 0 | D24: 0 | E24: 0
A25: CLNT nt_ckt_billed_live_disco_v2 | B25: Facility Circuit Charges Billed Disconnected | C25: 0 | D25: 0 | E25: 0
A26: Count of Invoices not zero Range | B26: Number Of Invoices | C26: 21B_ | D26: 0 | E26: 0
A27: Count Of Invoices not zero Range | B27: Number Of Invoices | C27: 21B_ | D27: 0 | E27: 0
A28: count_of_invoices_not_zero_range | B28: Number Of Invoices | C28: 21B_ | D28: 0 | E28: 0
A29: Deletions Under 5 Report | B29: Deletions Under 5 Report | C29: 0 | D29: 0 | E29: 0
A30: Deletions Under Report | B30: Deletions Under Report | C30: 0 | D30: 0 | E30: 0
A31: Detailed BAN Error Report | B31: Detailed BAN Error Report | C31: 4F_ | D31: 0 | E31: 0
A32: Detailed BAN Error Report - with extra research | B32: Detailed BAN Error Report | C32: 4F_ | D32: 0 | E32: 0
A33: Detailed CLLI Error Report | B33: Detailed CLLI Error Report | C33: 4H_ | D33: 0 | E33: 0
A34: Detailed CLLI Error Report - with extra research | B34: Detailed CLLI Error Report | C34: 4H_ | D34: 0 | E34: 0
A35: Duplicate File Processing Report | B35: Duplicate File Processing Report | C35: 5A_ | D35: 0 | E35: 0
A36: Exception Analysis Report | B36: Exception Analysis Report | C36: 4K_ | D36: 0 | E36: 0
A37: FA BAN Trending Report | B37: Facility BANS Trending Report | C37: 0 | D37: 0 | E37: 0
A38: FA Charges Summary | B38: FA Charges Summary | C38: 0 | D38: 0 | E38: 0
A39: FA Circuit Charges by CIC by CLLI | B39: FA Circuit Charges by CIC by CLLI | C39: 0 | D39: 0 | E39: 0
A40: Facility BANS Trending Report | B40: Facility BANS Trending Report | C40: 12D_ | D40: 12N_ | E40: 0
A41: Facility Circuit Charges Billed Disconnected | B41: Facility Circuit Charges Billed Disconnected | C41: 0 | D41: 0 | E41: 0
A42: Factor Change Audit Report | B42: Factor Change Audit Report | C42: 10_ | D42: 0 | E42: 0
A43: Factor Check Report with PVU | B43: Factor Check Report with PVU | C43: 10A_ | D43: 0 | E43: 0
A44: Factor Compare Report | B44: Factor Compare Report | C44: 10B_ | D44: 0 | E44: 0
A45: Factor Matrix Report | B45: Factor Matrix Report | C45: 0 | D45: 0 | E45: 0
A46: Fulfillment Report | B46: Fulfillment Report | C46: 0 | D46: 0 | E46: 0
A47: FUSC Charge By Circuit | B47: FUSC Charge By Circuit | C47: 0 | D47: 0 | E47: 0
A48: GL Extract | B48: GL Extract | C48: 0 | D48: 0 | E48: 0
A49: Invoice Balance | B49: Invoice Balance Report | C49: 0 | D49: 0 | E49: 0
A50: Invoice Balance Report | B50: Invoice Balance Report | C50: 0 | D50: 0 | E50: 0
A51: Invoice Balances by Jur with LPC | B51: Invoice Balances by Jur with LPC | C51: 0 | D51: 0 | E51: 0
A52: Invoice Balances by Jurisdiction | B52: Invoice Balances by Jurisdiction Report | C52: 0 | D52: 0 | E52: 0
A53: Invoice Balances by Jurisdiction Report | B53: Invoice Balances by Jurisdiction Report | C53: 0 | D53: 0 | E53: 0
A54: Invoice Count Range Report (non-zero balance) | B54: Number Of Invoices | C54: 21B_ | D54: 0 | E54: 0
A55: Invoice Count Report - Range | B55: Number Of Invoices | C55: 21B_ | D55: 0 | E55: 0
A56: Invoice Count Report (non-zero balances) | B56: Number Of Invoices | C56: 21B_ | D56: 0 | E56: 0
A57: Invoice Register Report | B57: Invoice Register Report | C57: 0 | D57: 0 | E57: 0
A58: Invoice Trending Report for Export - dir - jur | B58: Invoice Trending Report for Export - dir - jur | C58: 0 | D58: 0 | E58: 0
A59: Invoice Trending Report for Export (qty type dtl) | B59: Invoice Trending Report for Export (qty type dtl) | C59: 0 | D59: 0 | E59: 0
A60: Late Payment Charges | B60: Late Payment Charges | C60: 0 | D60: 0 | E60: 0
A61: Minutes and revenue billed by rate element | B61: Minutes and revenue billed by rate element | C61: 0 | D61: 0 | E61: 0
A62: MMR by Bill Date by Usg Pd by Direction by Prod | B62: MMR by Bill Date by Usg Pd by Direction by Prod | C62: 0 | D62: 0 | E62: 0
A63: MOU Entries Error Report | B63: MOU Entries Error Report | C63: 4L_ | D63: 0 | E63: 0
A64: MSG MOU Rev Export | B64: MMR Report | C64: 0 | D64: 0 | E64: 0
A65: MSG MOU REV Export - New | B65: MMR Report | C65: 0 | D65: 0 | E65: 0
A66: MSG MOU REV with LPC | B66: MSG MOU REV with LPC | C66: 0 | D66: 0 | E66: 0
A67: MSG_MOU_REV_export | B67: MMR Report | C67: 0 | D67: 0 | E67: 0
A68: NECA AS1000 | B68: NECA AS1000 | C68: 0 | D68: 0 | E68: 0
A69: NECA EC1050 | B69: NECA EC1050 | C69: 0 | D69: 0 | E69: 0
A70: OC&C GL Trans by BAN Report | B70: OCC Report | C70: 12P_ | D70: 0 | E70: 0
A71: OC&C Report | B71: OCC Report | C71: 12P_ | D71: 0 | E71: 0
A72: OCC GL Trans by BAN Report - New | B72: OCC Report | C72: 12P_ | D72: 0 | E72: 0
A73: Payment Report | B73: Payment Report | C73: 8_ | D73: 0 | E73: 0
A74: Payment Report - New | B74: Payment Report | C74: 8_ | D74: 0 | E74: 0
A75: Pre-Thresholding Report | B75: Pre-Thresholding Report | C75: 0 | D75: 0 | E75: 0
A76: Rev Analysis by CLLI | B76: Rev Analysis by CLLI | C76: 0 | D76: 0 | E76: 0
A77: Revenue Analysis | B77: Revenue Analysis | C77: 0 | D77: 0 | E77: 0
A78: Revenue Analysis - New | B78: Revenue Analysis | C78: 0 | D78: 0 | E78: 0
A79: SOC Change Audit Report | B79: SOC Change Audit Report | C79: 11_ | D79: 0 | E79: 0
A80: SOC Jurisdiction Report | B80: SOC Jurisdiction Report | C80: 0 | D80: 0 | E80: 0
A81: Sprint MOU Analysis for export | B81: Sprint MOU Analysis for export | C81: 0 | D81: 0 | E81: 0
A82: SW BANS Trending Report (qty type detail) | B82: SW BANS Trending Report | C82: 12C_ | D82: 0 | E82: 0
A83: SW Usage Charges Summary | B83: SW Usage Charges Summary | C83: 0 | D83: 0 | E83: 0
A84: Switch Terminating Intrastate Rev Report for NECA | B84: Switch Terminating Intrastate Rev Report for NECA | C84: 0 | D84: 0 | E84: 0
A85: Switched BANS Trending Report | B85: SW BANS Trending Report | C85: 12C_ | D85: 12M_ | E85: 19W_
A86: Switched BANS Trending Report - New | B86: SW BANS Trending Report | C86: 12C_ | D86: 12M_ | E86: 19W_
A87: Threshold Report by Period | B87: Threshold Report by Period | C87: 0 | D87: 0 | E87: 0
A88: Transaction Summary - bills only | B88: Transaction Summary Report | C88: 0 | D88: 0 | E88: 0
A89: Transaction Summary Report - New | B89: Transaction Summary Report | C89: 0 | D89: 0 | E89: 0
A90: Usage Balancing - Company Totals with Full Detail | B90: Usage Balancing - Company Totals with Full Detail | C90: 11B_ | D90: 0 | E90: 0
A91: Usage Balancing - Company, Ban Totals | B91: Usage Balancing | C91: 6_ | D91: 16_ | E91: 0
A92: Usage By Day Report | B92: Usage By Day Report | C92: 5D_ | D92: 5E-3months_ | E92: 0
A93: Usage by Day Report - New | B93: Usage By Day Report | C93: 5D_ | D93: 5E-3months_ | E93: 0
A94: Usage Verify by Size Report | B94: Usage Verify by Size Report | C94: 5C_ | D94: 0 | E94: 0
A95: Zero Rated MOU | B95: Zero Rated MOU | C95: 0 | D95: 0 | E95: 0
A96: Facility Billed with Disconnects | B96: Facility Circuit Charges Billed Disconnected | C96: 0 | D96: 0 | E96: 0
A97: 0 | B97: 0 | C97: 0 | D97: 0 | E97: 0
A98: 0 | B98: 0 | C98: 0 | D98: 0 | E98: 0
A99: 0 | B99: 0 | C99: 0 | D99: 0 | E99: 0
A100: 0 | B100: 0 | C100: 0 | D100: 0 | E100: 0
...

Sheet Sprint
A1: ='Specific Names Main'!A1 -> Before Renaming | B1: ='Specific Names Main'!B1 -> After Renaming | C1: ='Specific Names Main'!C1 -> Code 1 | D1: ='Specific Names Main'!D1 -> Code 2 | E1: ='Specific Names Main'!E1 -> Code 3
A2: ='Specific Names Main'!A2 -> Accounting Detailed Report | B2: ='Specific Names Main'!B2 -> Accounting Detailed Report | C2: ='Specific Names Main'!C2 -> 0 | D2: ='Specific Names Main'!D2 -> 0 | E2: ='Specific Names Main'!E2 -> 0
A3: ='Specific Names Main'!A3 -> Accounting Report | B3: ='Specific Names Main'!B3 -> Accounting Report | C3: ='Specific Names Main'!C3 -> 0 | D3: ='Specific Names Main'!D3 -> 0 | E3: ='Specific Names Main'!E3 -> 0
A4: ='Specific Names Main'!A4 -> Adjustment & OCC Report | B4: ='Specific Names Main'!B4 -> Adjustment & OCC Report | C4: ='Specific Names Main'!C4 -> 12Q_ | D4: ='Specific Names Main'!D4 -> 0 | E4: ='Specific Names Main'!E4 -> 0
A5: ='Specific Names Main'!A5 -> Adjustment GL Trans by BAN Report | B5: ='Specific Names Main'!B5 -> Adjustment Report | C5: ='Specific Names Main'!C5 -> 12O_ | D5: ='Specific Names Main'!D5 -> 0 | E5: ='Specific Names Main'!E5 -> 0
A6: ='Specific Names Main'!A6 -> Adjustment GL Trans by BAN Report - New | B6: ='Specific Names Main'!B6 -> Adjustment Report | C6: ='Specific Names Main'!C6 -> 12O_ | D6: ='Specific Names Main'!D6 -> 0 | E6: ='Specific Names Main'!E6 -> 0
A7: ='Specific Names Main'!A7 -> Adjustments GL Trans by BAN Report | B7: ='Specific Names Main'!B7 -> Adjustment Report | C7: ='Specific Names Main'!C7 -> 12O_ | D7: ='Specific Names Main'!D7 -> 0 | E7: ='Specific Names Main'!E7 -> 0
A8: ='Specific Names Main'!A8 -> Adjustments Not Posted Report | B8: ='Specific Names Main'!B8 -> Adjustments Not Posted Report | C8: ='Specific Names Main'!C8 -> 9F_ | D8: ='Specific Names Main'!D8 -> 0 | E8: ='Specific Names Main'!E8 -> 0
A9: ='Specific Names Main'!A9 -> Aged Trial Balance for Export | B9: ='Specific Names Main'!B9 -> Aged Trial Balance for Export Report | C9: ='Specific Names Main'!C9 -> 0 | D9: ='Specific Names Main'!D9 -> 0 | E9: ='Specific Names Main'!E9 -> 0
A10: ='Specific Names Main'!A10 -> Aged Trial Balance for Export - New | B10: ='Specific Names Main'!B10 -> Aged Trial Balance for Export Report | C10: ='Specific Names Main'!C10 -> 0 | D10: ='Specific Names Main'!D10 -> 0 | E10: ='Specific Names Main'!E10 -> 0
A11: ='Specific Names Main'!A11 -> Aged Trial Balance_for export | B11: ='Specific Names Main'!B11 -> Aged Trial Balance for Export Report | C11: ='Specific Names Main'!C11 -> 0 | D11: ='Specific Names Main'!D11 -> 0 | E11: ='Specific Names Main'!E11 -> 0
A12: ='Specific Names Main'!A12 -> Aged trial Balance | B12: ='Specific Names Main'!B12 -> Aged trial Balance Report | C12: ='Specific Names Main'!C12 -> 0 | D12: ='Specific Names Main'!D12 -> 0 | E12: ='Specific Names Main'!E12 -> 0
... A500: ='Specific Names Main'!A500 -> 0 | B500: ='Specific Names Main'!B500 -> 0 | C500: ='Specific Names Main'!C500 -> 0 | D500: ='Specific Names Main'!D500 -> 0 | E500: ='Specific Names Main'!E500 -> 0

Sheet BendTel
A1: BeforeRenaming | B1: AfterRenaming | C1: Code1 | D1: Code2 | E1: Code3
A2: Accounting Detailed Report | B2: Accounting Detailed Report
A3: Accounting Report | B3: Accounting Report
A4: Adjustment & OCC Report | B4: Adjustment & OCC Report | C4: 12Q_
A5: Adjustment GL Trans by BAN Report | B5: Adjustment Report | C5: 12O_
A6: Adjustment GL Trans by BAN Report - New | B6: Adjustment Report | C6: 12O_
A7: Adjustments GL Trans by BAN Report | B7: Adjustment Report | C7: 12O_
A8: Adjustments Not Posted Report | B8: Adjustments Not Posted Report | C8: 9F_
A9: Aged Trial Balance for Export | B9: Aged Trial Balance for Export Report
A10: Aged Trial Balance for Export - New | B10: Aged Trial Balance for Export Report
A11: Aged Trial Balance_for export | B11: Aged Trial Balance for Export Report
A12: Aged trial Balance | B12: Aged trial Balance Report
A13: Aged Trial Balance - New | B13: Aged trial Balance Report
A14: AUR History Stats | B14: AUR History Stats Report | C14: 4A_
A15: AUR History Stats Report | B15: AUR History Stats Report | C15: 4A_
A16: BAN List with Active Status and LPC Option | B16: BAN List with Active Status and LPC Option
A17: Bill By Period Report | B17: Bill By Period Report
A18: Bill Completion Check Report | B18: Bill Completion Check Report | C18: 12A_
A19: Billed by Period | B19: Bill By Period Report
A20: Billed by Period Report | B20: Bill By Period Report
A21: Billed by Period Report - New | B21: Bill By Period Report
A22: Billed Msg MOU Rev by BAN by EMR Jurisdiction | B22: Message MOU Revenue by BAN Report
A23: Billed Msg MOU Rev by CLLI by EMR Jurisdiction | B23: Message MOU Revenue by CLLI Report
A24: CLNT ly_invoice_balances_by_jur_cic | B24: Invoice Balance Report
A25: CLNT nt_ckt_billed_live_disco_v2 | B25: Facility Circuit Charges Billed Disconnected
A26: Count of Invoices not zero Range | B26: Number Of Invoices | C26: 21B_
A27: Count Of Invoices not zero Range | B27: Number Of Invoices | C27: 21B_
A28: count_of_invoices_not_zero_range | B28: Number Of Invoices | C28: 21B_
A29: Deletions Under 5 Report | B29: Deletions Under 5 Report
A30: Deletions Under Report | B30: Deletions Under Report
A31: Detailed BAN Error Report | B31: Detailed BAN Error Report | C31: 4F_
A32: Detailed BAN Error Report - with extra research | B32: Detailed BAN Error Report | C32: 4F_
A33: Detailed CLLI Error Report | B33: Detailed CLLI Error Report | C33: 4H_
A34: Detailed CLLI Error Report - with extra research | B34: Detailed CLLI Error Report | C34: 4H_
A35: Duplicate File Processing Report | B35: Duplicate File Processing Report | C35: 5A_
A36: Exception Analysis Report | B36: Exception Analysis Report | C36: 4K_
A37: FA BAN Trending Report | B37: Facility BANS Trending Report
A38: FA Charges Summary | B38: FA Charges Summary
A39: FA Circuit Charges by CIC by CLLI | B39: FA Circuit Charges by CIC by CLLI
A40: Facility BANS Trending Report | B40: Facility BANS Trending Report | C40: 12B_ | D40: 12D_ | E40: 12N_
A41: Facility Circuit Charges Billed Disconnected | B41: Facility Circuit Charges Billed Disconnected
A42: Factor Change Audit Report | B42: Factor Change Audit Report | C42: 1_
A43: Factor Check Report with PVU | B43: Factor Check Report with PVU | C43: 1A_
A44: Factor Compare Report | B44: Factor Compare Report | C44: 1B_
A45: Factor Matrix Report | B45: Factor Matrix Report
A46: Fulfillment Report | B46: Fulfillment Report
A47: FUSC Charge By Circuit | B47: FUSC Charge By Circuit
A48: GL Extract | B48: GL Extract
A49: Invoice Balance | B49: Invoice Balance Report
A50: Invoice Balance Report | B50: Invoice Balance Report
A51: Invoice Balances by Jur with LPC | B51: Invoice Balances by Jur with LPC
A52: Invoice Balances by Jurisdiction | B52: Invoice Balances by Jurisdiction Report
A53: Invoice Balances by Jurisdiction Report | B53: Invoice Balances by Jurisdiction Report
A54: Invoice Count Range Report (non-zero balance) | B54: Number Of Invoices | C54: 21B_
A55: Invoice Count Report - Range | B55: Number Of Invoices | C55: 21B_
A56: Invoice Count Report (non-zero balances) | B56: Number Of Invoices | C56: 21B_
A57: Invoice Register Report | B57: Invoice Register Report
A58: Invoice Trending Report for Export - dir - jur | B58: Invoice Trending Report for Export - dir - jur
A59: Invoice Trending Report for Export (qty type dtl) | B59: Invoice Trending Report for Export (qty type dtl)
A60: Late Payment Charges | B60: Late Payment Charges
A61: Minutes and revenue billed by rate element | B61: Minutes and revenue billed by rate element
A62: MMR by Bill Date by Usg Pd by Direction by Prod | B62: MMR by Bill Date by Usg Pd by Direction by Prod
A63: MOU Entries Error Report | B63: MOU Entries Error Report | C63: 4L_
A64: MSG MOU Rev Export | B64: MMR Report
A65: MSG MOU REV Export - New | B65: MMR Report
A66: MSG MOU REV with LPC | B66: MSG MOU REV with LPC
A67: MSG_MOU_REV_export | B67: MMR Report
A68: NECA AS1 | B68: NECA AS1
A69: NECA EC15 | B69: NECA EC15
A70: OC&C GL Trans by BAN Report | B70: OCC Report | C70: 12P_
A71: OC&C Report | B71: OCC Report | C71: 12P_
A72: OCC GL Trans by BAN Report - New | B72: OCC Report | C72: 12P_
A73: Payment Report | B73: Payment Report | C73: 8_
A74: Payment Report - New | B74: Payment Report | C74: 8_
A75: Pre-Thresholding Report | B75: Pre-Thresholding Report
A76: Rev Analysis by CLLI | B76: Rev Analysis by CLLI
A77: Revenue Analysis | B77: Revenue Analysis
A78: Revenue Analysis - New | B78: Revenue Analysis
A79: SOC Change Audit Report | B79: SOC Change Audit Report | C79: 11_
A80: SOC Jurisdiction Report | B80: SOC Jurisdiction Report
A81: Sprint MOU Analysis for export | B81: Sprint MOU Analysis for export
A82: SW BANS Trending Report (qty type detail) | B82: SW BANS Trending Report | C82: 12C_
A83: SW Usage Charges Summary | B83: SW Usage Charges Summary
A84: Switch Terminating Intrastate Rev Report for NECA | B84: Switch Terminating Intrastate Rev Report for NECA
A85: Switched BANS Trending Report | B85: SW BANS Trending Report | C85: 12B_ | D85: 12M_ | E85: 19W_
A86: Switched BANS Trending Report - New | B86: SW BANS Trending Report | C86: 12B_ | D86: 12M_ | E86: 19W_
A87: Threshold Report by Period | B87: Threshold Report by Period
A88: Transaction Summary - bills only | B88: Transaction Summary Report
A89: Transaction Summary Report - New | B89: Transaction Summary Report
A90: Usage Balancing - Company Totals with Full Detail | B90: Usage Balancing - Company Totals with Full Detail | C90: 11B_
A91: Usage Balancing - Company, Ban Totals | B91: Usage Balancing | C91: 6_ | D91: 13_ | E91: 16_
A92: Usage By Day Report | B92: Usage By Day Report | C92: 5D_ | D92: 5E-3months_
A93: Usage by Day Report - New | B93: Usage By Day Report | C93: 5D_ | D93: 5E-3months_
A94: Usage Verify by Size Report | B94: Usage Verify by Size Report | C94: 5C_
A95: Zero Rated MOU | B95: Zero Rated MOU
A96: Facility Billed with Disconnects | B96: Facility Circuit Charges Billed Disconnected

Sheet GCI
A1: Before Renaming | B1: After Renaming | C1: Code 1 | D1: Code 2 | E1: Code 3
A2: Accounting Detailed Report | B2: Accounting Detailed Report | C2: 0 | D2: 0 | E2: 0
A3: Accounting Report | B3: Accounting Report | C3: 0 | D3: 0 | E3: 0
A4: Adjustment & OCC Report | B4: Adjustment & OCC Report | C4: 12Q_ | D4: 0 | E4: 0
A5: Adjustment GL Trans by BAN Report | B5: Adjustment Report | C5: 12O_ | D5: 0 | E5: 0
A6: Adjustment GL Trans by BAN Report - New | B6: Adjustment Report | C6: 12O_ | D6: 0 | E6: 0
A7: Adjustments GL Trans by BAN Report | B7: Adjustment Report | C7: 12O_ | D7: 0 | E7: 0
A8: Adjustments Not Posted Report | B8: Adjustments Not Posted Report | C8: 9F_ | D8: 0 | E8: 0
A9: Aged Trial Balance for Export | B9: Aged Trial Balance for Export Report | C9: 0 | D9: 0 | E9: 0
A10: Aged Trial Balance for Export - New | B10: Aged Trial Balance for Export Report | C10: 0 | D10: 0 | E10: 0
A11: Aged Trial Balance_for export | B11: Aged Trial Balance for Export Report | C11: 0 | D11: 0 | E11: 0
A12: Aged trial Balance | B12: Aged trial Balance Report | C12: 0 | D12: 0 | E12: 0
A13: Aged Trial Balance - New | B13: Aged trial Balance Report | C13: 0 | D13: 0 | E13: 0
A14: AUR History Stats | B14: AUR History Stats Report | C14: 4A_ | D14: 0 | E14: 0
A15: AUR History Stats Report | B15: AUR History Stats Report | C15: 4A_ | D15: 0 | E15: 0
A16: BAN List with Active Status and LPC Option | B16: BAN List with Active Status and LPC Option | C16: 0 | D16: 0 | E16: 0
A17: Bill By Period Report | B17: Bill By Period Report | C17: 0 | D17: 0 | E17: 0
A18: Bill Completion Check Report | B18: Bill Completion Check Report | C18: 12A_ | D18: 0 | E18: 0
A19: Billed by Period | B19: Bill By Period Report | C19: 0 | D19: 0 | E19: 0
A20: Billed by Period Report | B20: Bill By Period Report | C20: 0 | D20: 0 | E20: 0
A21: Billed by Period Report - New | B21: Bill By Period Report | C21: 0 | D21: 0 | E21: 0
A22: Billed Msg MOU Rev by BAN by EMR Jurisdiction | B22: Message MOU Revenue by BAN Report | C22: 0 | D22: 0 | E22: 0
A23: Billed Msg MOU Rev by CLLI by EMR Jurisdiction | B23: Message MOU Revenue by CLLI Report | C23: 0 | D23: 0 | E23: 0
A24: CLNT ly_invoice_balances_by_jur_cic | B24: Invoice Balance Report | C24: 0 | D24: 0 | E24: 0
A25: CLNT nt_ckt_billed_live_disco_v2 | B25: Facility Circuit Charges Billed Disconnected | C25: 0 | D25: 0 | E25: 0
A26: Count of Invoices not zero Range | B26: Number Of Invoices | C26: 21B_ | D26: 0 | E26: 0
A27: Count Of Invoices not zero Range | B27: Number Of Invoices | C27: 21B_ | D27: 0 | E27: 0
A28: count_of_invoices_not_zero_range | B28: Number Of Invoices | C28: 21B_ | D28: 0 | E28: 0
A29: Deletions Under 5 Report | B29: Deletions Under 5 Report | C29: 0 | D29: 0 | E29: 0
A30: Deletions Under Report | B30: Deletions Under Report | C30: 0 | D30: 0 | E30: 0
A31: Detailed BAN Error Report | B31: Detailed BAN Error Report | C31: 4F_ | D31: 0 | E31: 0
A32: Detailed BAN Error Report - with extra research | B32: Detailed BAN Error Report | C32: 4F_ | D32: 0 | E32: 0
A33: Detailed CLLI Error Report | B33: Detailed CLLI Error Report | C33: 4H_ | D33: 0 | E33: 0
A34: Detailed CLLI Error Report - with extra research | B34: Detailed CLLI Error Report | C34: 4H_ | D34: 0 | E34: 0
A35: Duplicate File Processing Report | B35: Duplicate File Processing Report | C35: 5A_ | D35: 0 | E35: 0
A36: Exception Analysis Report | B36: Exception Analysis Report | C36: 4K_ | D36: 0 | E36: 0
A37: FA BAN Trending Report | B37: Facility BANS Trending Report | C37: 0 | D37: 0 | E37: 0
A38: FA Charges Summary | B38: FA Charges Summary | C38: 0 | D38: 0 | E38: 0
A39: FA Circuit Charges by CIC by CLLI | B39: FA Circuit Charges by CIC by CLLI | C39: 0 | D39: 0 | E39: 0
A40: Facility BANS Trending Report | B40: Facility BANS Trending Report | C40: 12B_ | D40: 12D_ | E40: 12N_
A41: Facility Circuit Charges Billed Disconnected | B41: Facility Circuit Charges Billed Disconnected | C41: 0 | D41: 0 | E41: 0
A42: Factor Change Audit Report | B42: Factor Change Audit Report | C42: 10_ | D42: 0 | E42: 0
A43: Factor Check Report with PVU | B43: Factor Check Report with PVU | C43: 10A_ | D43: 0 | E43: 0
A44: Factor Compare Report | B44: Factor Compare Report | C44: 10B_ | D44: 0 | E44: 0
A45: Factor Matrix Report | B45: Factor Matrix Report | C45: 0 | D45: 0 | E45: 0
A46: Fulfillment Report | B46: Fulfillment Report | C46: 0 | D46: 0 | E46: 0
A47: FUSC Charge By Circuit | B47: FUSC Charge By Circuit | C47: 0 | D47: 0 | E47: 0
A48: GL Extract | B48: GL Extract | C48: 0 | D48: 0 | E48: 0
A49: Invoice Balance | B49: Invoice Balance Report | C49: 0 | D49: 0 | E49: 0
A50: Invoice Balance Report | B50: Invoice Balance Report | C50: 0 | D50: 0 | E50: 0
A51: Invoice Balances by Jur with LPC | B51: Invoice Balances by Jur with LPC | C51: 0 | D51: 0 | E51: 0
A52: Invoice Balances by Jurisdiction | B52: Invoice Balances by Jurisdiction Report | C52: 0 | D52: 0 | E52: 0
A53: Invoice Balances by Jurisdiction Report | B53: Invoice Balances by Jurisdiction Report | C53: 0 | D53: 0 | E53: 0
A54: Invoice Count Range Report (non-zero balance) | B54: Number Of Invoices | C54: 21B_ | D54: 0 | E54: 0
A55: Invoice Count Report - Range | B55: Number Of Invoices | C55: 21B_ | D55: 0 | E55: 0
A56: Invoice Count Report (non-zero balances) | B56: Number Of Invoices | C56: 21B_ | D56: 0 | E56: 0
A57: Invoice Register Report | B57: Invoice Register Report | C57: 0 | D57: 0 | E57: 0
A58: Invoice Trending Report for Export - dir - jur | B58: Invoice Trending Report for Export - dir - jur | C58: 0 | D58: 0 | E58: 0
A59: Invoice Trending Report for Export (qty type dtl) | B59: Invoice Trending Report for Export (qty type dtl) | C59: 0 | D59: 0 | E59: 0
A60: Late Payment Charges | B60: Late Payment Charges | C60: 0 | D60: 0 | E60: 0
A61: Minutes and revenue billed by rate element | B61: Minutes and revenue billed by rate element | C61: 0 | D61: 0 | E61: 0
A62: MMR by Bill Date by Usg Pd by Direction by Prod | B62: MMR by Bill Date by Usg Pd by Direction by Prod | C62: 0 | D62: 0 | E62: 0
A63: MOU Entries Error Report | B63: MOU Entries Error Report | C63: 4L_ | D63: 0 | E63: 0
A64: MSG MOU Rev Export | B64: MMR Report | C64: 0 | D64: 0 | E64: 0
A65: MSG MOU REV Export - New | B65: MMR Report | C65: 0 | D65: 0 | E65: 0
A66: MSG MOU REV with LPC | B66: MSG MOU REV with LPC | C66: 0 | D66: 0 | E66: 0
A67: MSG_MOU_REV_export | B67: MMR Report | C67: 0 | D67: 0 | E67: 0
A68: NECA AS1000 | B68: NECA AS1000 | C68: 0 | D68: 0 | E68: 0
A69: NECA EC1050 | B69: NECA EC1050 | C69: 0 | D69: 0 | E69: 0
A70: OC&C GL Trans by BAN Report | B70: OCC Report | C70: 12P_ | D70: 0 | E70: 0
A71: OC&C Report | B71: OCC Report | C71: 12P_ | D71: 0 | E71: 0
A72: OCC GL Trans by BAN Report - New | B72: OCC Report | C72: 12P_ | D72: 0 | E72: 0
A73: Payment Report | B73: Payment Report | C73: 8_ | D73: 0 | E73: 0
A74: Payment Report - New | B74: Payment Report | C74: 8_ | D74: 0 | E74: 0
A75: Pre-Thresholding Report | B75: Pre-Thresholding Report | C75: 0 | D75: 0 | E75: 0
A76: Rev Analysis by CLLI | B76: Rev Analysis by CLLI | C76: 0 | D76: 0 | E76: 0
A77: Revenue Analysis | B77: Revenue Analysis | C77: 0 | D77: 0 | E77: 0
A78: Revenue Analysis - New | B78: Revenue Analysis | C78: 0 | D78: 0 | E78: 0
A79: SOC Change Audit Report | B79: SOC Change Audit Report | C79: 11_ | D79: 0 | E79: 0
A80: SOC Jurisdiction Report | B80: SOC Jurisdiction Report | C80: 0 | D80: 0 | E80: 0
A81: Sprint MOU Analysis for export | B81: Sprint MOU Analysis for export | C81: 0 | D81: 0 | E81: 0
A82: SW BANS Trending Report (qty type detail) | B82: SW BANS Trending Report | C82: 12C_ | D82: 0 | E82: 0
A83: SW Usage Charges Summary | B83: SW Usage Charges Summary | C83: 0 | D83: 0 | E83: 0
A84: Switch Terminating Intrastate Rev Report for NECA | B84: Switch Terminating Intrastate Rev Report for NECA | C84: 0 | D84: 0 | E84: 0
A85: Switched BANS Trending Report | B85: SW BANS Trending Report | C85: 12B_ | D85: 0 | E85: 0
A86: Switched BANS Trending Report - New | B86: SW BANS Trending Report | C86: 12B_ | D86: 0 | E86: 0
A87: Threshold Report by Period | B87: Threshold Report by Period | C87: 0 | D87: 0 | E87: 0
A88: Transaction Summary - bills only | B88: Transaction Summary Report | C88: 0 | D88: 0 | E88: 0
A89: Transaction Summary Report - New | B89: Transaction Summary Report | C89: 0 | D89: 0 | E89: 0
A90: Usage Balancing - Company Totals with Full Detail | B90: Usage Balancing - Company Totals with Full Detail | C90: 11B_ | D90: 0 | E90: 0
A91: Usage Balancing - Company, Ban Totals | B91: Usage Balancing | C91: 6_ | D91: 13_ | E91: 16_
A92: Usage By Day Report | B92: Usage By Day Report | C92: 5D_ | D92: 5E-3months_ | E92: 0
A93: Usage by Day Report - New | B93: Usage By Day Report | C93: 5D_ | D93: 5E-3months_ | E93: 0
A94: Usage Verify by Size Report | B94: Usage Verify by Size Report | C94: 5C_ | D94: 0 | E94: 0
A95: Zero Rated MOU | B95: Zero Rated MOU | C95: 0 | D95: 0 | E95: 0
A96: Facility Billed with Disconnects | B96: Facility Circuit Charges Billed Disconnected | C96: 0 | D96: 0 | E96: 0
A97: 0 | B97: 0 | C97: 0 | D97: 0 | E97: 0
A98: 0 | B98: 0 | C98: 0 | D98: 0 | E98: 0
A99: 0 | B99: 0 | C99: 0 | D99: 0 | E99: 0
A100: 0 | B100: 0 | C100: 0 | D100: 0 | E100: 0
...

Sheet Prefix
A1: Client | B1: prefix | C1: bill date
A2: Selectronics | B2: 0069_VT | C2: 01
A3: American_Broadband356D_MI | B3: 356D_MI | C3: 25
A4: American_Broadband509B_OH | B4: 509B_OH | C4: 20
A5: American_Broadband590G_IN | B5: 590G_IN | C5: 25
A6: BendTel | B6: 9627_OR | C6: 22
A7: MIEAC | B7: MIEAC | C7: 01
A8: ONVOY | B8: ONVOY | C8: 01
A9: Peerless_Network | B9: Peerless | C9: 05
A10: Neutral_TandemFA | B10: Combined_IQNT | C10: 01
A11: Neutral_TandemSW | B11: Combined | C11: 01
A12: Neutral_TandemSWO | B12: Combined_OSA | C12: 05
... A18: GCIFA | B18: GCI_FA | C18: 10
A19: Sprint

Sheet mps_database
A1: MPS Location | B1: Report Name | C1: File Location | D1: Coordinates
A2: 1 | B2: Verify Prior Period Post Date | D2: D17
A3: 1A | B3: Last date data was received. | D3: D18
A4: 1B | B4: Run Usage Balancing Report. Verify AUR = MOU | D4: D19
A5: 1C | B5: Client Final Approval of Usage Files | D5: D20
A6: 2 | B6: Verify From and To Cycle Dates | D6: D21
A7: 2A | B7: From cycle date: | D7: D22
A8: 2B | B8: To cycle date: | D8: D23
A9: 2C | B9: Bill Date | D9: D24
A10: 4A | B10: AUR History Stats Report | C10: K:\Client\MIEAC\Reports\2021\06_2021\MIEAC_060121_4A_AUR History Report.xls | D10: D32
A11: 4B | B11: Verify Bill Count | D11: D33
A12: 4C | B12: File Count: | D12: D34
A13: 4D | B13: Record Count: | D13: D35
A14: 4E | B14: Verify Count: | D14: D36
A15: 4F | B15: BAN Error Report | C15: K:\Client\MIEAC\Reports\2021\06_2021\MIEAC_060121_4F_Detailed BAN Error Report.xlsx | D15: D37
A16: 4G | B16: Set Up New BANs | D16: D38
A17: 4H | B17: CLLI Error Report | C17: K:\Client\MIEAC\Reports\2021\06_2021\MIEAC_060121_4H_No CLLI Report.xls | D17: D39
A18: 4I | B18: Set Up New CLLIs | D18: D40
A19: 4J | B19: CLLI Verification | D19: D41
A20: 4K | B20: Exception Analysis Report | C20: K:\Client\MIEAC\Reports\2021\06_2021\MIEAC_060121_4K_Exception Analysis Report.pdf | D20: D42
A21: 4L | B21: MOU Entries Error Report | C21: K:\Client\MIEAC\Reports\2021\06_2021\MIEAC_060121_4L_MOU Entries Error Report.pdf | D21: D43
A22: 4M | B22: NON MOU Entries Error Report | D22: D44
A23: 4N | B23: Process Fix Files | D23: D45
A24: 4O | B24: Install New Circuits | D24: D46
A25: 5 | B25: Analyze Files for Duplicate Processing and Non Processed Files | D25: D47
A26: 5A | B26: Duplicate File Processing Report | C26: K:\Client\MIEAC\Reports\2021\06_2021\MIEAC_060121_5A_Duplicate File Processing Report.pdf | D26: D48
A27: 5B | B27: Error Files Duplicate Report | D27: D49
A28: 5C | B28: Usage Verify by Size Report | C28: K:\Client\MIEAC\Reports\2021\06_2021\MIEAC_060121_5C_Usage Verify by Size Report.pdf | D28: D50
A29: 5D | B29: Usage By Day Report (NOTIFY CLIENT OF MISSING USAGE) | C29: K:\Client\MIEAC\Reports\2021\06_2021\MIEAC_060121_5D_Usage By Day Report.xlsx | D29: D51
A30: 5E-3MONTHS | B30: Usage By Day Report - 3 Month Period | C30: K:\Client\MIEAC\Reports\2021\06_2021\MIEAC_060121_5E-3MONTHS_Usage By Day Report.xlsx | D30: D52
A31: 5F | B31: Copy period error files to the following month Q folder | D31: D53
A32: 5G | B32: Zip files, analyze non-zipped files | D32: D54
A33: 5H | B33: Renewals, Changes, and/or New Rate | D33: D55
A34: 5I | B34: Disconnects | D34: D56
A35: 5J | B35: Preliminary Balancing Report | D35: D57
A36: 5k | B36: Duplicate File Processing Report by Name | D36: D58
A37: 5L | B37: Update Rate Change Calculator | D37: D59
A38: 5M | B38: Usage Variance Report | D38: D60
A39: 6 | B39: Usage Balancing Report | C39: K:\Client\MIEAC\Reports\2021\06_2021\MIEAC_060121_6_Company BAN Total Report.pdf | D39: D61
A40: 7 | B40: Enter MOU Exceptions | D40: D62
A41: 8 | B41: Enter/Post/Balance Payments | C41: K:\Client\MIEAC\Reports\2021\06_2021\MIEAC_060121_8_Payment Report.pdf | D41: D63
A42: 9 | B42: Enter/Post/Balance Adjustments. Include backup documentation. | D42: D64
A43: 9A | B43: Update OC&C Calculator | D43: D65
A44: 9B | B44: Enter OC&Cs, include backup documentation for entries. | D44: D66
A45: 9C | B45: Enter Adjustments, include backup documentation. | D45: D67
A46: 9D | B46: Adjustment Review Report | D46: D68
A47: 9E | B47: Post Adjustments | D47: D69
A48: 9F | B48: Adjustments Not Posted Report | C48: K:\Client\MIEAC\Reports\2021\06_2021\MIEAC_060121_9F_Adjustments Not Posted Report.pdf | D48: D70
A49: 9G | B49: Produce Bills for LPC Calculations | D49: D71
A50: 9H | B50: Aged Trial Balance for Late Payment Charges | D50: D72
A51: 9I | B51: Calculate Late Payment Charges | D51: D73
A52: 9J | B52: Apply Late Payment Charges | D52: D74
A53: 9K | B53: Produce Invoices with Late Payment Charges | D53: D75
A54: 9L | B54: Save Late Payment Invoices to Reports Folder on K | D54: D76
A55: 9M | B55: Validate Late Payment Charges/Invoices | D55: D77
A56: 10 | B56: Factor Change Audit Report | C56: K:\Client\MIEAC\Reports\2021\06_2021\MIEAC_060121_10_Factor Change Audit Report.pdf | D56: D78
A57: 10A | B57: Factor Check Report | C57: K:\Client\MIEAC\Reports\2021\06_2021\MIEAC_060121_10A_Factor Check Report with PVU.xlsx | D57: D79
A58: 10B | B58: Factor Compare Report | D58: D80
A59: 11 | B59: SOC Change Audit Report | C59: K:\Client\MIEAC\Reports\2021\06_2021\MIEAC_060121_11_SOC Change Audit Report.pdf | D59: D81
A60: 11A | B60: Enter Per Call Charges | D60: D82
A61: 11B | B61: Enter FGA Changes | D61: D83
A62: 11C | B62: Usage Balancing-Company BAN Total Report (Post FGA) | D62: D84
A63: 12 | B63: PRODUCE BILLS: Switched & Facility Check To, From, and Bill Dates | D63: D85
A64: 12A | B64: Bill Completion Check Report | D64: D86
A65: 12B | B65: Switched/Facility BANS Trending Report - as needed | C65: K:\Client\MIEAC\Reports\2021\06_2021\MIEAC_050121_12B_Switched BAN Trending Report.pdf | D65: D87
A66: 12C | B66: Switched BANS Trending Report (qty type dtl) | D66: D88
A67: 12D | B67: Facility BANS Trending Report | D67: D89
A68: 12E | B68: Delete Usage Where Appropriate | D68: D90
A69: 12F | B69: Active BANs | D69: D91
A70: 12G | B70: Validate Invoices with changes that impact billing | D70: D92
A71: 12H | B71: Revenue Balancing | D71: D93
A72: 12I | B72: Green Mountain Access | D72: D94
A73: 12J | B73: Fairpoint Manual Usage Delete and Entry | D73: D95
A74: 12K | B74: FUSF Tax - Calulate and Create OCC | D74: D96
A75: 12L | B75: Reproduce ALL invoices to include changes | D75: D97
A76: 12M | B76: Switched BANs Trending Report | D76: D98
A77: 12N | B77: Facility BANs Trending Report | D77: D99
A78: 12O | B78: Adjustments Report | C78: K:\Client\MIEAC\Reports\2021\06_2021\MIEAC_050121_12O_Adjustment Report.pdf | D78: D100
A79: 12P | B79: OCCs Report | D79: D101
A80: 12Q | B80: Adjustments & OC&Cs Report | D80: D102
A81: 12R | B81: Switched BANS Trending Report Validation *NEW* | D81: D103
A82: 13 | B82: Usage Balancing Report | C82: K:\Client\MIEAC\Reports\2021\06_2021\MIEAC_050121_13_Company BAN Total Report.pdf | D82: D104
A83: 13A | B83: Do a Preliminary Balance prior to Thesholding | D83: D105
A84: 13B | B84: Pre-ATB Report | D84: D106
A85: 13C | B85: MMR by BAN | C85: K:\Client\MIEAC\Reports\2021\06_2021\MIEAC_050121_13C_MMR by BAN.pdf | D85: D107
A86: 13D | B86: Pre Transaction Summary Report | C86: K:\Client\MIEAC\Reports\2021\06_2021\MIEAC_050121_13D_Pre-Transaction Summary.pdf | D86: D108
A87: 13E | B87: Adjustment GL Trans by BAN Report | D87: D109
A88: 13F | B88: OC&C GL Trans by BAN Report | D88: D110
A89: 13G | B89: Zero Rated Traffic Report | D89: D111
A90: 13H | B90: Late Payment Charges | D90: D112
A91: 13.I | B91: FUSF Report | D91: D113
A92: 14 | B92: Thresholding Report | D92: D114
A93: 14A | B93: BANs for Thresholding Report | C93: K:\Client\MIEAC\Reports\2021\06_2021\MIEAC_050121_14A_Pre Threshold.xls | D93: D115
A94: 14B | B94: Perform the action of Thresholding | D94: D116
A95: 14C | B95: Thresheld BANs Report | C95: K:\Client\MIEAC\Reports\2021\06_2021\MIEAC_050121_14C_Post Threshold.xls | D95: D117
A96: 15 | B96: Delete Usage for All Invoices Meeting Client Criteria | D96: D118
A97: 15A | B97: Identify BANs to Delete Usage | D97: D119
A98: 15B | B98: Delete usage | D98: D120
A99: 15C | B99: Manual PLU Adjustments | D99: D121
A100: 15D | B100: Term 3 to 1 Report - Reciprocal Compensation | D100: D122
...

Sheet Specific Names draft
A1: Name | B1: Pattern | C1: Array
A2: Payment Report | B2: <prefix>_<mm>10<yy>_<ar>Payment Report | C2: 8
A3: Factor Change Audit Report | B3: <prefix>_<mm>10<yy>_<ar>Factor Change Audit Report | C3: 10
A4: SOC Change Audit Report | B4: <prefix>_<mm>10<yy>_<ar>SOC Change Audit Report | C4: 11
A5: Factor Check Report with PVU | B5: <prefix>_<mm>10<yy>_<ar>Factor Check Report with PVU | C5: 10A
A6: Usage Balancing - Company Totals with Full Detail | B6: <prefix>_<mm>10<yy>_<ar>FGA Usage Balance Details | C6: 11B
A7: Bill Completion Check Report | B7: <prefix>_<mm>10<yy>_<ar>Bill Completion Check Report | C7: 12A
A8: Switched BANS Trending Report | B8: <prefix>_<mm>10<yy>_<ar>Switched BANS Trending Report | C8: 12B
A9: Adjustment GL Trans by BAN Report | B9: <prefix>_<mm>10<yy>_<ar>Adjustments Report | C9: 12O
A10: OC&C GL Trans by BAN Report | B10: <prefix>_<mm>10<yy>_<ar>OCCs Report | C10: 12P
A11: count_of_invoices_not_zero_range | B11: <prefix>_<mm>10<yy>_<ar>Invoice Count | C11: 21B
A12: AUR History Stats Report | B12: <prefix>_<mm>10<yy>_<ar>AUR History Stats Report | C12: 4A
A13: Detailed BAN Error Report - with extra research | B13: <prefix>_<mm>10<yy>_<ar>Detailed BAN Error Report | C13: 4F
A14: Detailed CLLI Error Report | B14: <prefix>_<mm>10<yy>_<ar>Detailed CLLI Error Report | C14: 4H
A15: Exception Analysis Report | B15: <prefix>_<mm>10<yy>_<ar>Exception Analysis Report | C15: 4K
A16: MOU Entries Error Report | B16: <prefix>_<mm>10<yy>_<ar>MOU Entries Error Report | C16: 4L
... A21: Adjustments Not Posted Report | B21: <prefix>_<mm>10<yy>_<ar>Adjustments Not Posted Report | C21: 9F
A22: Aged Trial Balance for Export | B22: <prefix>_<mm>10<yy>_<ar>Aged Trial Balance for Export Report
A23: Billed by Period | B23: <prefix>_<mm>10<yy>_<ar>Billed by Period Report
A24: Billed Msg MOU Rev by BAN by EMR Jurisdiction | B24: <prefix>_<mm>10<yy>_<ar>Message MOU Revenue by BAN Report
A25: Billed Msg MOU Rev by CLLI by EMR Jurisdiction | B25: <prefix>_<mm>10<yy>_<ar>Message MOU Revenue by CLLI Report
A26: Minutes and revenue billed by rate element | B26: <prefix>_<mm>10<yy>_<ar>Minutes and Revenue Billed By Rate Element Report
A27: SW Usage Charges Summary | B27: <prefix>_<mm>10<yy>_<ar>SW Usage Charges Summary Report
A28: Transaction Summary - bills only | B28: <prefix>_<mm>10<yy>_<ar>Transaction Summary Report
A29: Payment Report | B29: ="<prefix>_<mm>05<yy>_<ar>"&A29 -> <prefix>_<mm>05<yy>_<ar>Payment Report | C29: 8
A30: Factor Change Audit Report | B30: ="<prefix>_<mm>05<yy>_<ar>"&A30 -> <prefix>_<mm>05<yy>_<ar>Factor Change Audit Report | C30: 10
A31: SOC Change Audit Report | B31: ="<prefix>_<mm>05<yy>_<ar>"&A31 -> <prefix>_<mm>05<yy>_<ar>SOC Change Audit Report | C31: 11
A32: Factor Check Report with PVU | B32: <prefix>_<mm>05<yy>_<ar>Factor Check Report | C32: 10A
A33: Bill Completion Check Report | B33: ="<prefix>_<mm>05<yy>_<ar>"&A33 -> <prefix>_<mm>05<yy>_<ar>Bill Completion Check Report | C33: 12A
A34: Switched BANS Trending Report | B34: <prefix>_<mm>05<yy>_<ar>Switched BANS Trending Report | C34: 12B
A35: Adjustment GL Trans by BAN Report | B35: <prefix>_<mm>05<yy>_<ar>Adjustments Report | C35: 12O
A36: OC&C GL Trans by BAN Report | B36: <prefix>_<mm>05<yy>_<ar>OCCs Report | C36: 12P
A37: count_of_invoices_not_zero_range | B37: <prefix>_<mm>05<yy>_<ar>Invoice Count | C37: 21B
A38: AUR History Stats Report | B38: <prefix>_<mm>05<yy>_<ar>AUR History Stats Report | C38: 4A
A39: Detailed BAN Error Report - with extra research | B39: <prefix>_<mm>05<yy>_<ar>Detailed BAN Error Report | C39: 4F
A40: Detailed CLLI Error Report | B40: <prefix>_<mm>05<yy>_<ar>Detailed CLLI Error Report | C40: 4H
A41: Exception Analysis Report | B41: <prefix>_<mm>05<yy>_<ar>Exception Analysis Report | C41: 4K
A42: MOU Entries Error Report | B42: <prefix>_<mm>05<yy>_<ar>MOU Entries Error Report | C42: 4L
A43: Duplicate File Processing Report | B43: <prefix>_<mm>05<yy>_<ar>Duplicate File Processing Report | C43: 5A
A44: Usage Verify by Size Report | B44: <prefix>_<mm>05<yy>_<ar>Usage Verify by Size Report | C44: 5C
A45: Usage By Day Report | B45: <prefix>_<mm>05<yy>_<ar>Usage By Day Report | C45: 5D,5E-3months
... A47: Adjustments Not Posted Report | B47: <prefix>_<mm>05<yy>_<ar>Adjustments Not Posted Report | C47: 9F
A48: Aged Trial Balance for Export | B48: <prefix>_<mm>05<yy>_<ar>Aged Trial Balance for Export Report
A49: Billed by Period | B49: <prefix>_<mm>05<yy>_<ar>Billed by Period Report
A50: Billed Msg MOU Rev by BAN by EMR Jurisdiction | B50: <prefix>_<mm>05<yy>_<ar>Message MOU Revenue by BAN Report
A51: Billed Msg MOU Rev by CLLI by EMR Jurisdiction | B51: <prefix>_<mm>05<yy>_<ar>Message MOU Revenue by CLLI Report
A52: Minutes and revenue billed by rate element | B52: <prefix>_<mm>05<yy>_<ar>Minutes and Revenue Billed By Rate Element Report
A53: SW Usage Charges Summary | B53: <prefix>_<mm>05<yy>_<ar>SW Usage Charges Summary Report
A54: Transaction Summary - bills only | B54: <prefix>_<mm>05<yy>_<ar>Transaction Summary Report
A55: Factor Change Audit Report | B55: <prefix>_<mm>10<yy>_<ar>Factor Audit Report | C55: 10
A56: SOC Change Audit Report | B56: <prefix>_<mm>10<yy>_<ar>SOC Change Report | C56: 11
A57: Bill Completion Check Report | B57: <prefix>_<mm>10<yy>_<ar>Bill Completion Check | C57: 12A
A58: Facility BANS Trending Report | B58: <prefix>_<mm>10<yy>_<ar>Facility BANS Trending Report | C58: 12B
A59: Adjustment GL Trans by BAN Report | B59: <prefix>_<mm>10<yy>_<ar>Adjustments Report | C59: 12O
A60: OC&C GL Trans by BAN Report | B60: <prefix>_<mm>10<yy>_<ar>OCCs Report | C60: 12P
A61: count_of_invoices_not_zero_range | B61: <prefix>_<mm>10<yy>_<ar>Invoice Count | C61: 21B
A62: Payment Report | B62: ="<prefix>_<mm>10<yy>_<ar>"&A62 -> <prefix>_<mm>10<yy>_<ar>Payment Report | C62: 8
A63: Adjustments Not Posted Report | B63: ="<prefix>_<mm>10<yy>_<ar>"&A63 -> <prefix>_<mm>10<yy>_<ar>Adjustments Not Posted Report | C63: 9F
A64: FA Charges Summary | B64: <prefix>_<mm>10<yy>_<ar>FA Charges Summary Report
A65: CLNT nt_ckt_billed_live_disco_v2 | B65: <prefix>_<mm>10<yy>_<ar>Facility Circuit Charges Billed Disconnected
A66: FA Circuit Charges by CIC by CLLI | B66: <prefix>_<mm>10<yy>_<ar>FA Circuit Charges by CIC by CLLI Report
A67: Aged Trial Balance for Export | B67: <prefix>_<mm>10<yy>_<ar>Aged Trial Balance for Export Report
A68: FUSC Charge By Circuit | B68: <prefix>_<mm>10<yy>_<ar>FUSC Charge By Circuit
A69: Transaction Summary - bills only | B69: <prefix>_<mm>10<yy>_<ar>Transaction Summary Report
A70: AUR History Stats Report | B70: ="<prefix>_<mm>_25_<yyyy>_<ar>"&A70 -> <prefix>_<mm>_25_<yyyy>_<ar>AUR History Stats Report | C70: 4A | D70: 1
A71: Detailed BAN Error Report | B71: ="<prefix>_<mm>_25_<yyyy>_<ar>"&A71 -> <prefix>_<mm>_25_<yyyy>_<ar>Detailed BAN Error Report | C71: 4F | D71: 2
A72: Detailed BAN Error Report - with extra research | B72: <prefix>_<mm>_25_<yyyy>_<ar>Detailed BAN Error Report | C72: 4F | D72: 2
A73: Detailed CLLI Error Report | B73: ="<prefix>_<mm>_25_<yyyy>_<ar>"&A73 -> <prefix>_<mm>_25_<yyyy>_<ar>Detailed CLLI Error Report | C73: 4H | D73: 3
A74: Exception Analysis Report | B74: ="<prefix>_<mm>_25_<yyyy>_<ar>"&A74 -> <prefix>_<mm>_25_<yyyy>_<ar>Exception Analysis Report | C74: 4K | D74: 4
A75: MOU Entries Error Report | B75: ="<prefix>_<mm>_25_<yyyy>_<ar>"&A75 -> <prefix>_<mm>_25_<yyyy>_<ar>MOU Entries Error Report | C75: 4L | D75: 5
A76: Duplicate File Processing Report | B76: ="<prefix>_<mm>_25_<yyyy>_<ar>"&A76 -> <prefix>_<mm>_25_<yyyy>_<ar>Duplicate File Processing Report | C76: 5A | D76: 6
A77: Usage Verify by Size Report | B77: ="<prefix>_<mm>_25_<yyyy>_<ar>"&A77 -> <prefix>_<mm>_25_<yyyy>_<ar>Usage Verify by Size Report | C77: 5C | D77: 7
A78: Usage by Day Report | B78: ="<prefix>_<mm>_25_<yyyy>_<ar>"&A78 -> <prefix>_<mm>_25_<yyyy>_<ar>Usage by Day Report | C78: 5D,5E_3 Month Period | D78: 8 | E78: this report is run twice (5E), the 2nd time with different parameters, and named differently (adding "3 Month Period" at the end). Suggestions?
A79: Usage Balancing - Company, Ban Totals | B79: <prefix>_<mm>_25_<yyyy>_<ar>Usage Balancing Report | C79: 6,13,16 | D79: 9
A80: Payment Report | B80: ="<prefix>_<mm>_25_<yyyy>_<ar>"&A80 -> <prefix>_<mm>_25_<yyyy>_<ar>Payment Report | C80: 8 | D80: 10
A81: Adjustments Not Posted Report | B81: ="<prefix>_<mm>_25_<yyyy>_<ar>"&A81 -> <prefix>_<mm>_25_<yyyy>_<ar>Adjustments Not Posted Report | C81: 9F | D81: 11
A82: Factor Change Audit Report | B82: ="<prefix>_<mm>_25_<yyyy>_<ar>"&A82 -> <prefix>_<mm>_25_<yyyy>_<ar>Factor Change Audit Report | C82: 10 | D82: 12
A83: Factor Check Report with PVU | B83: <prefix>_<mm>_25_<yyyy>_<ar>Factor Check Report | C83: 10A | D83: 13
A84: Factor Compare Report | B84: ="<prefix>_<mm>_25_<yyyy>_<ar>"&A84 -> <prefix>_<mm>_25_<yyyy>_<ar>Factor Compare Report | C84: 10B | D84: 14
A85: SOC Change Audit Report | B85: ="<prefix>_<mm>_25_<yyyy>_<ar>"&A85 -> <prefix>_<mm>_25_<yyyy>_<ar>SOC Change Audit Report | C85: 11 | D85: 15
A86: Bill Completion Check Report | B86: ="<prefix>_<mm>_25_<yyyy>_<ar>"&A86 -> <prefix>_<mm>_25_<yyyy>_<ar>Bill Completion Check Report | C86: 12A | D86: 16
A87: Switched BANS Trending Report | B87: ="<prefix>_<mm>_25_<yyyy>_<ar>"&A87 -> <prefix>_<mm>_25_<yyyy>_<ar>Switched BANS Trending Report | C87: 12C | D87: 17 | E87: cannont run via multi/AutoReports; send to client
A88: Adjustment & OCC Report | B88: ="<prefix>_<mm>_25_<yyyy>_<ar>"&A88 -> <prefix>_<mm>_25_<yyyy>_<ar>Adjustment & OCC Report | C88: 12Q,s2c | D88: 18
A89: Deletions Under Report | B89: ="<prefix>_<mm>_25_<yyyy>_<ar>"&A89 -> <prefix>_<mm>_25_<yyyy>_<ar>Deletions Under Report | C89: 15A Before,15F After | D89: 19
A90: Invoice Count Report (non-zero balances) | B90: <prefix>_<mm>_25_<yyyy>_<ar>Number of Invoices | C90: 21B | D90: 20
A91: Aged Trial Balance for Export | B91: <prefix>_<mm>_25_<yyyy>_<ar>Aged Trial Balance for Export Report | D91: 21 | E91: send to client
A92: Aged trial Balance | B92: <prefix>_<mm>_25_<yyyy>_<ar>Aged trial Balance Report | D92: 22 | E92: send to client
A93: Billed by Period Report | B93: ="<prefix>_<mm>_25_<yyyy>_<ar>"&A93 -> <prefix>_<mm>_25_<yyyy>_<ar>Billed by Period Report | D93: 23 | E93: send to client
A94: Billed Msg MOU Rev by BAN by EMR Jurisdiction | B94: <prefix>_<mm>_25_<yyyy>_<ar>Message MOU Revenue by BAN Report | D94: 24 | E94: cannont run via multi/AutoReports; send to client
A95: Transaction Summary - bills only | B95: ="<prefix>_<mm>_25_<yyyy>_<ar>"&A95 -> <prefix>_<mm>_25_<yyyy>_<ar>Transaction Summary - bills only | D95: 25 | E95: send to client
A96: Invoice Balances by Jurisdiction | B96: ="<prefix>_<mm>_25_<yyyy>_<ar>"&A96 -> <prefix>_<mm>_25_<yyyy>_<ar>Invoice Balances by Jurisdiction | D96: 26 | E96: Combined
A97: Invoice Register Report | B97: ="<prefix>_<mm>_25_<yyyy>_<ar>"&A97 -> <prefix>_<mm>_25_<yyyy>_<ar>Invoice Register Report | D97: 27 | E97: Combined
A98: AUR History Stats Report | B98: ="<prefix>_<mm>_22_<yy>_<ar>"&A98 -> <prefix>_<mm>_22_<yy>_<ar>AUR History Stats Report | C98: 4A | D98: 1
A99: Detailed BAN Error Report | B99: ="<prefix>_<mm>_22_<yy>_<ar>"&A99 -> <prefix>_<mm>_22_<yy>_<ar>Detailed BAN Error Report | C99: 4F | D99: 2
A100: Detailed BAN Error Report - with extra research | B100: <prefix>_<mm>_22_<yy>_<ar>Detailed BAN Error Report | C100: 4F | D100: 2
A101: Detailed CLLI Error Report | B101: ="<prefix>_<mm>_22_<yy>_<ar>"&A101 -> <prefix>_<mm>_22_<yy>_<ar>Detailed CLLI Error Report | C101: 4H | D101: 3
A102: Exception Analysis Report | B102: ="<prefix>_<mm>_22_<yy>_<ar>"&A102 -> <prefix>_<mm>_22_<yy>_<ar>Exception Analysis Report | C102: 4K | D102: 4
A103: MOU Entries Error Report | B103: ="<prefix>_<mm>_22_<yy>_<ar>"&A103 -> <prefix>_<mm>_22_<yy>_<ar>MOU Entries Error Report | C103: 4L | D103: 5
A104: Duplicate File Processing Report | B104: ="<prefix>_<mm>_22_<yy>_<ar>"&A104 -> <prefix>_<mm>_22_<yy>_<ar>Duplicate File Processing Report | C104: 5A | D104: 6
A105: Usage Verify by Size Report | B105: ="<prefix>_<mm>_22_<yy>_<ar>"&A105 -> <prefix>_<mm>_22_<yy>_<ar>Usage Verify by Size Report | D105: 7
...

Sheet Patterns
A1: AMBB | B1: <prefix>_<mm>_25_<yyyy>_<ar>Revenue
A2: Bendtel | B2: <prefix>_<mm>_22_<yy>_<ar>SOC Rate Comparison between companies
A3: GCI SW | B3: <prefix>_<mm><cy><yy>_<ar>Switched Billing Account - Factor Report
A4: MIEAC | B4: <prefix>_<mm>01<yy>_<ar>Summary of Adjustments Report
A5: MTA FA | B5: <prefix>_<mm>10<yy>_<ar>Factor Audit Report
A6: MTA RC | B6: <prefix>_<mm>05<yy>_<ar>Payment Report
A7: MTA SW | B7: <prefix>_<mm>10<yy>_<ar>Payment Report
A8: NT FA | B8: Combined_<prefix>_<mm><cy><yy>_<ar>Payment Report
A9: NT SW | B9: Combined_<prefix>_<mm><cy><yy>_<ar>Payments
B10: Combined_<mm><yy>_<ar>Bill Completion Check Report
A11: Onvoy | B11: <prefix>_<mm>01<yy>_<ar>Payment Report
A12: Perless | B12: <prefix>_<mm>-05-<yy>_<ar>Usage Verify by Size Report
A13: Selectronics | B13: <prefix>_<mm>01<yy>_<ar>Payment Report
A14: Sprint | B14: <prefix>_<mm>20<yyyy>_<ar>Detailed BAN Error Report

Sheet Draft
A1: Name | B1: Pattern | C1: Array
A2: Payment Report | B2: ="<prefix>_<mm>10<yy>_<ar>"&A2 -> <prefix>_<mm>10<yy>_<ar>Payment Report | C2: 8
A3: Factor Change Audit Report | B3: ="<prefix>_<mm>10<yy>_<ar>"&A3 -> <prefix>_<mm>10<yy>_<ar>Factor Change Audit Report | C3: 10
A4: SOC Change Audit Report | B4: ="<prefix>_<mm>10<yy>_<ar>"&A4 -> <prefix>_<mm>10<yy>_<ar>SOC Change Audit Report | C4: 11
A5: Factor Check Report with PVU | B5: ="<prefix>_<mm>10<yy>_<ar>"&A5 -> <prefix>_<mm>10<yy>_<ar>Factor Check Report with PVU | C5: 10A
A6: Usage Balancing - Company Totals with Full Detail | B6: <prefix>_<mm>10<yy>_<ar>FGA Usage Balance Details | C6: 11B
A7: Bill Completion Check Report | B7: ="<prefix>_<mm>10<yy>_<ar>"&A7 -> <prefix>_<mm>10<yy>_<ar>Bill Completion Check Report | C7: 12A
A8: Switched BANS Trending Report | B8: ="<prefix>_<mm>10<yy>_<ar>"&A8 -> <prefix>_<mm>10<yy>_<ar>Switched BANS Trending Report | C8: 12B
A9: Adjustment GL Trans by BAN Report | B9: <prefix>_<mm>10<yy>_<ar>Adjustments Report | C9: 12O
A10: OC&C GL Trans by BAN Report | B10: <prefix>_<mm>10<yy>_<ar>OCCs Report | C10: 12P
A11: count_of_invoices_not_zero_range | B11: <prefix>_<mm>10<yy>_<ar>Invoice Count | C11: 21B
A12: AUR History Stats Report | B12: ="<prefix>_<mm>10<yy>_<ar>"&A12 -> <prefix>_<mm>10<yy>_<ar>AUR History Stats Report | C12: 4A
A13: Detailed BAN Error Report - with extra research | B13: <prefix>_<mm>10<yy>_<ar>Detailed BAN Error Report | C13: 4F
A14: Detailed CLLI Error Report | B14: ="<prefix>_<mm>10<yy>_<ar>"&A14 -> <prefix>_<mm>10<yy>_<ar>Detailed CLLI Error Report | C14: 4H
A15: Exception Analysis Report | B15: ="<prefix>_<mm>10<yy>_<ar>"&A15 -> <prefix>_<mm>10<yy>_<ar>Exception Analysis Report | C15: 4K
A16: MOU Entries Error Report | B16: ="<prefix>_<mm>10<yy>_<ar>"&A16 -> <prefix>_<mm>10<yy>_<ar>MOU Entries Error Report | C16: 4L
A17: Duplicate File Processing Report | B17: ="<prefix>_<mm>10<yy>_<ar>"&A17 -> <prefix>_<mm>10<yy>_<ar>Duplicate File Processing Report | C17: 5A
A18: Usage Verify by Size Report | B18: ="<prefix>_<mm>10<yy>_<ar>"&A18 -> <prefix>_<mm>10<yy>_<ar>Usage Verify by Size Report | C18: 5C
A19: Usage By Day Report | B19: ="<prefix>_<mm>10<yy>_<ar>"&A19 -> <prefix>_<mm>10<yy>_<ar>Usage By Day Report | C19: 5D,5E-3months
A20: Usage Balancing - Company, Ban Totals | B20: <prefix>_<mm>10<yy>_<ar>Usage Balancing | C20: 6,11C-Post-FGA,13
A21: Adjustments Not Posted Report | B21: ="<prefix>_<mm>10<yy>_<ar>"&A21 -> <prefix>_<mm>10<yy>_<ar>Adjustments Not Posted Report | C21: 9F
A22: Aged Trial Balance for Export | B22: <prefix>_<mm>10<yy>_<ar>Aged Trial Balance for Export Report
A23: Billed by Period | B23: <prefix>_<mm>10<yy>_<ar>Billed by Period Report
A24: Billed Msg MOU Rev by BAN by EMR Jurisdiction | B24: <prefix>_<mm>10<yy>_<ar>Message MOU Revenue by BAN Report
A25: Billed Msg MOU Rev by CLLI by EMR Jurisdiction | B25: <prefix>_<mm>10<yy>_<ar>Message MOU Revenue by CLLI Report
A26: Minutes and revenue billed by rate element | B26: <prefix>_<mm>10<yy>_<ar>Minutes and Revenue Billed By Rate Element Report
A27: SW Usage Charges Summary | B27: <prefix>_<mm>10<yy>_<ar>SW Usage Charges Summary Report
A28: Transaction Summary - bills only | B28: <prefix>_<mm>10<yy>_<ar>Transaction Summary Report
A29: Access MSG and MOU billed by CLLI,FG,CIC | B29: ="<prefix>_<mm>10<yy>_<ar>"&A29 -> <prefix>_<mm>10<yy>_<ar>Access MSG and MOU billed by CLLI,FG,CIC
A30: Adjustments Detail Report - Posted | B30: ="<prefix>_<mm>10<yy>_<ar>"&A30 -> <prefix>_<mm>10<yy>_<ar>Adjustments Detail Report - Posted
A31: Adjustments Detail Report - Unposted | B31: ="<prefix>_<mm>10<yy>_<ar>"&A31 -> <prefix>_<mm>10<yy>_<ar>Adjustments Detail Report - Unposted
A32: Aged trial Balance | B32: ="<prefix>_<mm>10<yy>_<ar>"&A32 -> <prefix>_<mm>10<yy>_<ar>Aged trial Balance
A33: Aged Trial Balance by Company | B33: ="<prefix>_<mm>10<yy>_<ar>"&A33 -> <prefix>_<mm>10<yy>_<ar>Aged Trial Balance by Company
A34: Amount billed/disputed/settled by month/carrier | B34: ="<prefix>_<mm>10<yy>_<ar>"&A34 -> <prefix>_<mm>10<yy>_<ar>Amount billed/disputed/settled by month/carrier
A35: Amount billed/disputed/settled by qtr/carrier | B35: ="<prefix>_<mm>10<yy>_<ar>"&A35 -> <prefix>_<mm>10<yy>_<ar>Amount billed/disputed/settled by qtr/carrier
A36: Amount billed-disputed-settled by month-carrier | B36: ="<prefix>_<mm>10<yy>_<ar>"&A36 -> <prefix>_<mm>10<yy>_<ar>Amount billed-disputed-settled by month-carrier
A37: Amount billed-disputed-settled by qtr-carrier | B37: ="<prefix>_<mm>10<yy>_<ar>"&A37 -> <prefix>_<mm>10<yy>_<ar>Amount billed-disputed-settled by qtr-carrier
A38: AS1000 Report | B38: ="<prefix>_<mm>10<yy>_<ar>"&A38 -> <prefix>_<mm>10<yy>_<ar>AS1000 Report
A39: AUR History Stats | B39: ="<prefix>_<mm>10<yy>_<ar>"&A39 -> <prefix>_<mm>10<yy>_<ar>AUR History Stats
A40: AUR History Stats (Seconds) | B40: ="<prefix>_<mm>10<yy>_<ar>"&A40 -> <prefix>_<mm>10<yy>_<ar>AUR History Stats (Seconds)
... A156: Wire Center Report | B156: ="<prefix>_<mm>10<yy>_<ar>"&A156 -> <prefix>_<mm>10<yy>_<ar>Wire Center Report
A157: Payment Report | B157: ="<prefix>_<mm>05<yy>_<ar>"&A157 -> <prefix>_<mm>05<yy>_<ar>Payment Report | C157: 8
A158: Factor Change Audit Report | B158: ="<prefix>_<mm>05<yy>_<ar>"&A158 -> <prefix>_<mm>05<yy>_<ar>Factor Change Audit Report | C158: 10
A159: SOC Change Audit Report | B159: ="<prefix>_<mm>05<yy>_<ar>"&A159 -> <prefix>_<mm>05<yy>_<ar>SOC Change Audit Report | C159: 11
A160: Factor Check Report with PVU | B160: <prefix>_<mm>05<yy>_<ar>Factor Check Report | C160: 10A
A161: Bill Completion Check Report | B161: ="<prefix>_<mm>05<yy>_<ar>"&A161 -> <prefix>_<mm>05<yy>_<ar>Bill Completion Check Report | C161: 12A
A162: Switched BANS Trending Report | B162: <prefix>_<mm>05<yy>_<ar>Switched BANS Trending Report | C162: 12B
A163: Adjustment GL Trans by BAN Report | B163: <prefix>_<mm>05<yy>_<ar>Adjustments Report | C163: 12O
A164: OC&C GL Trans by BAN Report | B164: <prefix>_<mm>05<yy>_<ar>OCCs Report | C164: 12P
A165: count_of_invoices_not_zero_range | B165: <prefix>_<mm>05<yy>_<ar>Invoice Count | C165: 21B
A166: AUR History Stats Report | B166: <prefix>_<mm>05<yy>_<ar>AUR History Stats Report | C166: 4A
A167: Detailed BAN Error Report - with extra research | B167: <prefix>_<mm>05<yy>_<ar>Detailed BAN Error Report | C167: 4F
A168: Detailed CLLI Error Report | B168: <prefix>_<mm>05<yy>_<ar>Detailed CLLI Error Report | C168: 4H
A169: Exception Analysis Report | B169: <prefix>_<mm>05<yy>_<ar>Exception Analysis Report | C169: 4K
A170: MOU Entries Error Report | B170: <prefix>_<mm>05<yy>_<ar>MOU Entries Error Report | C170: 4L
A171: Duplicate File Processing Report | B171: <prefix>_<mm>05<yy>_<ar>Duplicate File Processing Report | C171: 5A
A172: Usage Verify by Size Report | B172: <prefix>_<mm>05<yy>_<ar>Usage Verify by Size Report | C172: 5C
A173: Usage By Day Report | B173: <prefix>_<mm>05<yy>_<ar>Usage By Day Report | C173: 5D,5E-3months
... A175: Adjustments Not Posted Report | B175: <prefix>_<mm>05<yy>_<ar>Adjustments Not Posted Report | C175: 9F
A176: Aged Trial Balance for Export | B176: <prefix>_<mm>05<yy>_<ar>Aged Trial Balance for Export Report
A177: Billed by Period | B177: <prefix>_<mm>05<yy>_<ar>Billed by Period Report
A178: Billed Msg MOU Rev by BAN by EMR Jurisdiction | B178: <prefix>_<mm>05<yy>_<ar>Message MOU Revenue by BAN Report
A179: Billed Msg MOU Rev by CLLI by EMR Jurisdiction | B179: <prefix>_<mm>05<yy>_<ar>Message MOU Revenue by CLLI Report
A180: Minutes and revenue billed by rate element | B180: <prefix>_<mm>05<yy>_<ar>Minutes and Revenue Billed By Rate Element Report
A181: SW Usage Charges Summary | B181: <prefix>_<mm>05<yy>_<ar>SW Usage Charges Summary Report
A182: Transaction Summary - bills only | B182: <prefix>_<mm>05<yy>_<ar>Transaction Summary Report
A183: Access MSG and MOU billed by CLLI,FG,CIC | B183: ="<prefix>_<mm>05<yy>_<ar>"&A183 -> <prefix>_<mm>05<yy>_<ar>Access MSG and MOU billed by CLLI,FG,CIC
A184: Adjustments Detail Report - Posted | B184: ="<prefix>_<mm>05<yy>_<ar>"&A184 -> <prefix>_<mm>05<yy>_<ar>Adjustments Detail Report - Posted
A185: Adjustments Detail Report - Unposted | B185: ="<prefix>_<mm>05<yy>_<ar>"&A185 -> <prefix>_<mm>05<yy>_<ar>Adjustments Detail Report - Unposted
A186: Aged trial Balance | B186: ="<prefix>_<mm>05<yy>_<ar>"&A186 -> <prefix>_<mm>05<yy>_<ar>Aged trial Balance
A187: Aged Trial Balance by Company | B187: ="<prefix>_<mm>05<yy>_<ar>"&A187 -> <prefix>_<mm>05<yy>_<ar>Aged Trial Balance by Company
A188: Amount billed/disputed/settled by month/carrier | B188: ="<prefix>_<mm>05<yy>_<ar>"&A188 -> <prefix>_<mm>05<yy>_<ar>Amount billed/disputed/settled by month/carrier
A189: Amount billed/disputed/settled by qtr/carrier | B189: ="<prefix>_<mm>05<yy>_<ar>"&A189 -> <prefix>_<mm>05<yy>_<ar>Amount billed/disputed/settled by qtr/carrier
A190: Amount billed-disputed-settled by month-carrier | B190: ="<prefix>_<mm>05<yy>_<ar>"&A190 -> <prefix>_<mm>05<yy>_<ar>Amount billed-disputed-settled by month-carrier
A191: Amount billed-disputed-settled by qtr-carrier | B191: ="<prefix>_<mm>05<yy>_<ar>"&A191 -> <prefix>_<mm>05<yy>_<ar>Amount billed-disputed-settled by qtr-carrier
A192: AS1000 Report | B192: ="<prefix>_<mm>05<yy>_<ar>"&A192 -> <prefix>_<mm>05<yy>_<ar>AS1000 Report
A193: AUR History Stats | B193: ="<prefix>_<mm>05<yy>_<ar>"&A193 -> <prefix>_<mm>05<yy>_<ar>AUR History Stats
A194: AUR History Stats (Seconds) | B194: ="<prefix>_<mm>05<yy>_<ar>"&A194 -> <prefix>_<mm>05<yy>_<ar>AUR History Stats (Seconds)
... A196: AUR History Summary by Day | B196: ="<prefix>_<mm>05<yy>_<ar>"&A196 -> <prefix>_<mm>05<yy>_<ar>AUR History Summary by Day
A197: Billed Minutes by Inter/Intra State | B197: ="<prefix>_<mm>10<yy>_<ar>"&A197 -> <prefix>_<mm>10<yy>_<ar>Billed Minutes by Inter/Intra State
A198: Billed Minutes by Inter-Intra State | B198: ="<prefix>_<mm>10<yy>_<ar>"&A198 -> <prefix>_<mm>10<yy>_<ar>Billed Minutes by Inter-Intra State
A199: Billed Minutes by Jurisdiction | B199: ="<prefix>_<mm>10<yy>_<ar>"&A199 -> <prefix>_<mm>10<yy>_<ar>Billed Minutes by Jurisdiction
A200: Billed minutes by Quarter by Inter/Intra State | B200: ="<prefix>_<mm>10<yy>_<ar>"&A200 -> <prefix>_<mm>10<yy>_<ar>Billed minutes by Quarter by Inter/Intra State
A201: Billed minutes by Quarter by Inter-Intra State | B201: ="<prefix>_<mm>10<yy>_<ar>"&A201 -> <prefix>_<mm>10<yy>_<ar>Billed minutes by Quarter by Inter-Intra State
A202: Billed Minutes by Quarter by Jurisdiction | B202: ="<prefix>_<mm>10<yy>_<ar>"&A202 -> <prefix>_<mm>10<yy>_<ar>Billed Minutes by Quarter by Jurisdiction
A203: Billed Msg MOU Rev by BAN by Jurisdiction | B203: ="<prefix>_<mm>10<yy>_<ar>"&A203 -> <prefix>_<mm>10<yy>_<ar>Billed Msg MOU Rev by BAN by Jurisdiction
A204: Billed Msg MOU Rev by CLLI by Jurisdiction | B204: ="<prefix>_<mm>10<yy>_<ar>"&A204 -> <prefix>_<mm>10<yy>_<ar>Billed Msg MOU Rev by CLLI by Jurisdiction
A205: CLNT aur_usage_by_day_co_v3 | B205: ="<prefix>_<mm>10<yy>_<ar>"&A205 -> <prefix>_<mm>10<yy>_<ar>CLNT aur_usage_by_day_co_v3
A206: CLNT billed_by_period_for_exp_4_v2 | B206: ="<prefix>_<mm>10<yy>_<ar>"&A206 -> <prefix>_<mm>10<yy>_<ar>CLNT billed_by_period_for_exp_4_v2
A207: CLNT cbeyond_m_m_r_to_export_v2 | B207: ="<prefix>_<mm>10<yy>_<ar>"&A207 -> <prefix>_<mm>10<yy>_<ar>CLNT cbeyond_m_m_r_to_export_v2
A208: CLNT ckt_billed_live_disco_v1 | B208: ="<prefix>_<mm>10<yy>_<ar>"&A208 -> <prefix>_<mm>10<yy>_<ar>CLNT ckt_billed_live_disco_v1
... A311: Wire Center Report | B311: ="<prefix>_<mm>10<yy>_<ar>"&A311 -> <prefix>_<mm>10<yy>_<ar>Wire Center Report
A312: Payment Report | B312: ="<prefix>_<mm>05<yy>_<ar>"&A312 -> <prefix>_<mm>05<yy>_<ar>Payment Report | C312: 8
A313: Factor Change Audit Report | B313: ="<prefix>_<mm>05<yy>_<ar>"&A313 -> <prefix>_<mm>05<yy>_<ar>Factor Change Audit Report | C313: 10
A314: SOC Change Audit Report | B314: ="<prefix>_<mm>05<yy>_<ar>"&A314 -> <prefix>_<mm>05<yy>_<ar>SOC Change Audit Report | C314: 11
A315: Factor Check Report with PVU | B315: <prefix>_<mm>05<yy>_<ar>Factor Check Report | C315: 10A
A316: Bill Completion Check Report | B316: ="<prefix>_<mm>05<yy>_<ar>"&A316 -> <prefix>_<mm>05<yy>_<ar>Bill Completion Check Report | C316: 12A
A317: Switched BANS Trending Report | B317: <prefix>_<mm>05<yy>_<ar>Switched BANS Trending Report | C317: 12B
A318: Adjustment GL Trans by BAN Report | B318: <prefix>_<mm>05<yy>_<ar>Adjustments Report | C318: 12O
A319: OC&C GL Trans by BAN Report | B319: <prefix>_<mm>05<yy>_<ar>OCCs Report | C319: 12P
...

Sheet mps_database1
A1: ID | B1: MPSLocation | C1: ReportName | D1: FileLocation | E1: Coordinates
A2: 1 | B2: 1 | C2: Verify Prior Period Post Date | E2: D17
A3: 2 | B3: 1A | C3: Last date data was received. | E3: D18
A4: 3 | B4: 1B | C4: Run Usage Balancing Report. Verify AUR = MOU | E4: D19
A5: 4 | B5: 1C | C5: Client Final Approval of Usage Files | E5: D20
A6: 5 | B6: 2 | C6: Verify From and To Cycle Dates | E6: D21
A7: 6 | B7: 2A | C7: From cycle date: | E7: D22
A8: 7 | B8: 2B | C8: To cycle date: | E8: D23
A9: 8 | B9: 2C | C9: Bill Date | E9: D24
A10: 9 | B10: 4A | C10: AUR History Stats Report | E10: D32
A11: 10 | B11: 4B | C11: Verify Bill Count | E11: D33
A12: 11 | B12: 4C | C12: File Count: | E12: D34
A13: 12 | B13: 4D | C13: Record Count: | E13: D35
... A282: 281 | B282: 21BTTS | C282: Number of InvoicesTTS | E282: F228
A283: 282 | B283: 19QOSA | C283: Invoice Balances by Jur with LPCOSA
A284: 283 | B284: 19QTTS | C284: Invoice Balances by Jur with LPCTTS
